Workbook

Sheet Business Problem
A1: "What factors are associated with employee attrition, which employee groups are at greatest risk, and how can People Analytics help the organisation take proactive action?"
A6: "How would you approach building an attrition-risk model?"
A8: You could eventually answer:
A10: "I'd start by defining the business problem rather than immediately choosing a model. I'd first understand whether the organisation is trying to reduce voluntary attrition overall or address a specific population or capability risk. I'd then validate and prepare the employee data, analyse historical attrition patterns and identify potential drivers across factors such as tenure, engagement, compensation, progression and workforce characteristics.
A15: I'd establish a baseline and then develop a predictive model to identify employees or populations with elevated risk. I'd validate the model carefully and, importantly, focus on interpretability because the output needs to support responsible people decisions. I'd then translate the results into actionable insights for HR and managers rather than simply giving them a risk score. Finally, I'd measure whether interventions actually reduce attrition over time."

Sheet Expectation
A1: For a senior People Analytics role, I'd actually expect you to first show something like:
A3: Overall attrition rate
A5: → Which groups are leaving?
A7: → What factors appear associated with attrition?
A9: → Can we predict who is at higher risk?
A11: → What should HR do about it?

Sheet Practical & Solution Workflow
A1: Our practical workflow
A3: We'll work through:
A5: 1. Define the business question
A6: 2. Explore the workforce data
A7: 3. Identify the target variable — Attrition
A8: 4. Prepare and clean the data
A9: 5. Explore drivers of attrition
A10: 6. Build a baseline model
A11: 7. Build a predictive model
A12: 8. Evaluate model performance
A13: 9. Interpret the key attrition drivers
A14: 10. Create an attrition-risk dashboard
... A24: 4. Actionable — What should HR do about it?

Sheet Dashboard 1_Descriptive  Leave
B3: LEAVERS DASHBOARD — WHO LEFT?
C5: ='Dashboard Pivots'!B5 -> 851 | F5: ='Dashboard Pivots'!B10 -> 149 | I5: ='Dashboard Pivots'!C16 -> 0.149 | O5: ='Dashboard Pivots'!D6 -> 4.5073826
C6: Headcount | F6: No of Leavers | I6: Attrition Rate | N6: Average Tenure of Leavers
B39: The Leavers Dashboard provides a profile of the 149 employees who exited the organisation, highlighting where leavers are concentrated across department, age, tenure, job level, country and performance. It helps identify the characteristics and workforce segments contributing most to overall employee turnover.

Sheet Dashboard 2_Attrition Analysis
B2: ATTRITION DASHBOARD — WHERE IS THE RISK HIGHEST?
B41: The Attrition Dashboard examines the 14.9% overall attrition rate across key workforce segments, identifying areas where employees are leaving at disproportionately higher rates. It highlights variation in attrition by department, gender, age, tenure, job level and country, helping to identify priority populations for further investigation and retention action.

Sheet Dashboard 3_Diagnostic Drivers
B2: DIAGNOSTIC ATTRITION DASHBOARD — WHAT IS ASSOCIATED WITH EMPLOYEE ATTRITION?
Z19: S
B29: The Diagnostic Dashboard shows that attrition is concentrated among employees with low engagement score, lower compensation positioning, longer periods since salary increases,limited career progression and overtime.

Sheet Dashboard 4_Predictive Attritio
B2: PREDICTIVE ATTRITION DASHBOARD — WHO IS MOST LIKELY TO LEAVE?
B4: Model Performance
B5: ='Predictive Pivots'!C7 -> 0.728 | F5: ='Predictive Pivots'!C8 -> 0.1127 | J5: ='Predictive Pivots'!C9 -> 0.149 | N5: ='Predictive Pivots'!C10 -> 1000
B6: ='Predictive Pivots'!B7 -> ROC-AUC | F6: ='Predictive Pivots'!B8 -> Brier Score | J6: ='Predictive Pivots'!B9 -> Overall Attrition | N6: ='Predictive Pivots'!B10 -> Employees
B7: Model Discrimination | F7: Probability accuracy | J7: 149 of 1000 employees | N7: Development dataset
B46: Logistic regression was used to estimate employee attrition probability. Categorical variables were dummy encoded using defined reference categories. Model coefficients were estimated using Excel Solver by maximising log-likelihood. Model development performance: ROC-AUC 0.728; Brier Score 0.1127.
B50: Key insight:The highest-risk 10% of employees contains 31.5% of historical leavers, increasing to 48.3% within the top 20%. This indicates that the model concentrates a disproportionately large share of leavers toward the top of its risk ranking.
B55: Slide 0: Methodology & Model Setup (The Foundation)
B56: Objective: Build a data-driven system to identify individual employee attrition risk and uncover key turnover drivers.
B57: The Engine: Built a custom Logistic Regression Model using Maximum Likelihood Estimation (MLE) optimization directly within Excel.
B58: Data Processing: Evaluated a comprehensive mix of continuous numbers (Age, Tenure, Salary) and categorical text fields (Departments, Role, Country).
B59: Reference Baselines: To prevent mathematical redundancy, standard reference groups were systematically dropped. All resulting insights are measured as a direct contrast to our Baseline Employee Profile:
B60: Gender / Department: Male / Operations
B61: Country / Job Level: United Kingdom / Professional
B62: Work Type / Performance: Hybrid Arrangement / Meets Expectations
B64: 🎛️ How to Handle the Presentation
B65: When you present Slide 0, use it to build immediate credibility with your audience before showing the risks. You can explain it like this:
... B100: Answer: "Absolutely. The underlying math of Logistic Regression is identical whether executed in Python, R, or Excel. We verified the model using a Brier Score, which returned a 0.11271. Since 0.25 represents random guessing and 0.00 is mathematical perfection, a score of 0.11 mathematically proves that this Excel configuration has captured highly stable, genuine operational patterns."

Sheet Predictive Pivots
B2: A. Model performance — top row
B4: Use KPI cards:
I5: Row Labels | J5: Count of Age | K5: Sum of Leaver flag | M5: Row Labels | N5: Sum of Leaver flag | P5: Top 10 | S5: Top 20 | V5: Top 30 | Y5: Top 40 | AB5: Top 50
B6: KPI | C6: Value | I6: High | J6: 148 | K6: 33 | L6: 1 | M6: 0.80396423 | N6: 0 | P6: 0.80396423 | Q6: 0 | S6: 0.80396423 | T6: 0 | V6: 0.80396423 | W6: 0 | Y6: 0.80396423 | Z6: 0 | AB6: 0.80396423 | AC6: 0
B7: ROC-AUC | C7: 0.728 | I7: Low | J7: 437 | K7: 30 | L7: 2 | M7: 0.77735127 | N7: 1 | P7: 0.77735127 | Q7: 1 | S7: 0.77735127 | T7: 1 | V7: 0.77735127 | W7: 1 | Y7: 0.77735127 | Z7: 1 | AB7: 0.77735127 | AC7: 1
B8: Brier Score | C8: 0.1127 | I8: Moderate | J8: 313 | K8: 38 | L8: 3 | M8: 0.63332627 | N8: 1 | P8: 0.63332627 | Q8: 1 | S8: 0.63332627 | T8: 1 | V8: 0.63332627 | W8: 1 | Y8: 0.63332627 | Z8: 1 | AB8: 0.63332627 | AC8: 1
B9: Overall Attrition | C9: 0.149 | I9: Very High | J9: 102 | K9: 48 | L9: 4 | M9: 0.62273774 | N9: 1 | P9: 0.62273774 | Q9: 1 | S9: 0.62273774 | T9: 1 | V9: 0.62273774 | W9: 1 | Y9: 0.62273774 | Z9: 1 | AB9: 0.62273774 | AC9: 1
B10: Employees | C10: 1000 | I10: Grand Total | J10: 1000 | K10: 149 | L10: 5 | M10: 0.61475339 | N10: 0 | P10: 0.61475339 | Q10: 0 | S10: 0.61475339 | T10: 0 | V10: 0.61475339 | W10: 0 | Y10: 0.61475339 | Z10: 0 | AB10: 0.61475339 | AC10: 0
L11: 6 | M11: 0.5909025 | N11: 0 | P11: 0.5909025 | Q11: 0 | S11: 0.5909025 | T11: 0 | V11: 0.5909025 | W11: 0 | Y11: 0.5909025 | Z11: 0 | AB11: 0.5909025 | AC11: 0
L12: 7 | M12: 0.58939698 | N12: 1 | P12: 0.58939698 | Q12: 1 | S12: 0.58939698 | T12: 1 | V12: 0.58939698 | W12: 1 | Y12: 0.58939698 | Z12: 1 | AB12: 0.58939698 | AC12: 1
L13: 8 | M13: 0.58302494 | N13: 1 | P13: 0.58302494 | Q13: 1 | S13: 0.58302494 | T13: 1 | V13: 0.58302494 | W13: 1 | Y13: 0.58302494 | Z13: 1 | AB13: 0.58302494 | AC13: 1
B14: Predicted Probability | C14: Risk band | D14: Employees | E14: Leavers | F14: Actual Attrition | G14: Lift | L14: 9 | M14: 0.56549404 | N14: 1 | P14: 0.56549404 | Q14: 1 | S14: 0.56549404 | T14: 1 | V14: 0.56549404 | W14: 1 | Y14: 0.56549404 | Z14: 1 | AB14: 0.56549404 | AC14: 1
B15: <10% | C15: Low | D15: 437 | E15: 30 | F15: =E15/D15 -> 0.068649886 | G15: =F15/$F$19 -> 0.46073749 | L15: 10 | M15: 0.56221316 | N15: 1 | P15: 0.56221316 | Q15: 1 | S15: 0.56221316 | T15: 1 | V15: 0.56221316 | W15: 1 | Y15: 0.56221316 | Z15: 1 | AB15: 0.56221316 | AC15: 1
B16: 10%-<20% | C16: Moderate | D16: 313 | E16: 38 | F16: =E16/D16 -> 0.12140575 | G16: =F16/$F$19 -> 0.8148037 | L16: 11 | M16: 0.5578065 | N16: 1 | P16: 0.5578065 | Q16: 1 | S16: 0.5578065 | T16: 1 | V16: 0.5578065 | W16: 1 | Y16: 0.5578065 | Z16: 1 | AB16: 0.5578065 | AC16: 1
B17: 20%-<30% | C17: High | D17: 148 | E17: 33 | F17: =E17/D17 -> 0.22297297 | G17: =F17/$F$19 -> 1.4964629 | L17: 12 | M17: 0.54293268 | N17: 0 | P17: 0.54293268 | Q17: 0 | S17: 0.54293268 | T17: 0 | V17: 0.54293268 | W17: 0 | Y17: 0.54293268 | Z17: 0 | AB17: 0.54293268 | AC17: 0
B18: >=30% | C18: Very high | D18: 102 | E18: 48 | F18: =E18/D18 -> 0.47058824 | G18: =F18/$F$19 -> 3.1583103 | L18: 13 | M18: 0.53610589 | N18: 0 | P18: 0.53610589 | Q18: 0 | S18: 0.53610589 | T18: 0 | V18: 0.53610589 | W18: 0 | Y18: 0.53610589 | Z18: 0 | AB18: 0.53610589 | AC18: 0
C19: Total | D19: =SUM(D15:D18) -> 1000 | E19: =SUM(E15:E18) -> 149 | F19: =E19/D19 -> 0.149 | G19: =F19/$F$19 -> 1 | I19: Risk | J19: (Multiple Items) | L19: 14 | M19: 0.52092307 | N19: 0 | P19: 0.52092307 | Q19: 0 | S19: 0.52092307 | T19: 0 | V19: 0.52092307 | W19: 0 | Y19: 0.52092307 | Z19: 0 | AB19: 0.52092307 | AC19: 0
L20: 15 | M20: 0.51757816 | N20: 0 | P20: 0.51757816 | Q20: 0 | S20: 0.51757816 | T20: 0 | V20: 0.51757816 | W20: 0 | Y20: 0.51757816 | Z20: 0 | AB20: 0.51757816 | AC20: 0
B21: Risk band | C21: Employees | D21: % Workforce | I21: Row Labels | J21: Employees | L21: 16 | M21: 0.51282052 | N21: 0 | P21: 0.51282052 | Q21: 0 | S21: 0.51282052 | T21: 0 | V21: 0.51282052 | W21: 0 | Y21: 0.51282052 | Z21: 0 | AB21: 0.51282052 | AC21: 0
B22: Low | C22: 437 | D22: =C22/$C$26 -> 0.437 | I22: Finance | J22: 44 | L22: 17 | M22: 0.51255153 | N22: 1 | P22: 0.51255153 | Q22: 1 | S22: 0.51255153 | T22: 1 | V22: 0.51255153 | W22: 1 | Y22: 0.51255153 | Z22: 1 | AB22: 0.51255153 | AC22: 1
B23: Moderate | C23: 313 | D23: =C23/$C$26 -> 0.313 | I23: IT | J23: 40 | L23: 18 | M23: 0.50933054 | N23: 0 | P23: 0.50933054 | Q23: 0 | S23: 0.50933054 | T23: 0 | V23: 0.50933054 | W23: 0 | Y23: 0.50933054 | Z23: 0 | AB23: 0.50933054 | AC23: 0
B24: High | C24: 148 | D24: =C24/$C$26 -> 0.148 | I24: Operations | J24: 39 | L24: 19 | M24: 0.48949508 | N24: 1 | P24: 0.48949508 | Q24: 1 | S24: 0.48949508 | T24: 1 | V24: 0.48949508 | W24: 1 | Y24: 0.48949508 | Z24: 1 | AB24: 0.48949508 | AC24: 1
B25: Very High | C25: 102 | D25: =C25/$C$26 -> 0.102 | I25: Claims | J25: 38 | L25: 20 | M25: 0.4801273 | N25: 1 | P25: 0.4801273 | Q25: 1 | S25: 0.4801273 | T25: 1 | V25: 0.4801273 | W25: 1 | Y25: 0.4801273 | Z25: 1 | AB25: 0.4801273 | AC25: 1
B26: Total | C26: 1000 | D26: =C26/$C$26 -> 1 | I26: Sales | J26: 36 | L26: 21 | M26: 0.47561535 | N26: 1 | P26: 0.47561535 | Q26: 1 | S26: 0.47561535 | T26: 1 | V26: 0.47561535 | W26: 1 | Y26: 0.47561535 | Z26: 1 | AB26: 0.47561535 | AC26: 1
I27: HR | J27: 26 | L27: 22 | M27: 0.47045928 | N27: 0 | P27: 0.47045928 | Q27: 0 | S27: 0.47045928 | T27: 0 | V27: 0.47045928 | W27: 0 | Y27: 0.47045928 | Z27: 0 | AB27: 0.47045928 | AC27: 0
I28: Marketing | J28: 16 | L28: 23 | M28: 0.47033961 | N28: 1 | P28: 0.47033961 | Q28: 1 | S28: 0.47033961 | T28: 1 | V28: 0.47033961 | W28: 1 | Y28: 0.47033961 | Z28: 1 | AB28: 0.47033961 | AC28: 1
I29: Underwriting | J29: 11 | L29: 24 | M29: 0.46656345 | N29: 1 | P29: 0.46656345 | Q29: 1 | S29: 0.46656345 | T29: 1 | V29: 0.46656345 | W29: 1 | Y29: 0.46656345 | Z29: 1 | AB29: 0.46656345 | AC29: 1
B30: Employees Targeted | C30: Leavers Captured | D30: % of Leavers Captured | E30: Lift | I30: Grand Total | J30: 250 | L30: 25 | M30: 0.45997489 | N30: 1 | P30: 0.45997489 | Q30: 1 | S30: 0.45997489 | T30: 1 | V30: 0.45997489 | W30: 1 | Y30: 0.45997489 | Z30: 1 | AB30: 0.45997489 | AC30: 1
B31: Top 10% | C31: 47 | D31: =C31/149 -> 0.31543624 | L31: 26 | M31: 0.45753775 | N31: 0 | P31: 0.45753775 | Q31: 0 | S31: 0.45753775 | T31: 0 | V31: 0.45753775 | W31: 0 | Y31: 0.45753775 | Z31: 0 | AB31: 0.45753775 | AC31: 0
B32: Top 20% | C32: 72 | D32: =C32/149 -> 0.48322148 | L32: 27 | M32: 0.45085488 | N32: 1 | P32: 0.45085488 | Q32: 1 | S32: 0.45085488 | T32: 1 | V32: 0.45085488 | W32: 1 | Y32: 0.45085488 | Z32: 1 | AB32: 0.45085488 | AC32: 1
B33: Top 30% | C33: 88 | D33: =C33/149 -> 0.59060403 | L33: 28 | M33: 0.44209629 | N33: 1 | P33: 0.44209629 | Q33: 1 | S33: 0.44209629 | T33: 1 | V33: 0.44209629 | W33: 1 | Y33: 0.44209629 | Z33: 1 | AB33: 0.44209629 | AC33: 1
B34: Top 40% | C34: 98 | D34: =C34/149 -> 0.65771812 | I34: Risk | J34: (Multiple Items) | L34: 29 | M34: 0.4390298 | N34: 0 | P34: 0.4390298 | Q34: 0 | S34: 0.4390298 | T34: 0 | V34: 0.4390298 | W34: 0 | Y34: 0.4390298 | Z34: 0 | AB34: 0.4390298 | AC34: 0
B35: Top 50% | C35: 114 | D35: =C35/149 -> 0.76510067 | L35: 30 | M35: 0.43696886 | N35: 0 | P35: 0.43696886 | Q35: 0 | S35: 0.43696886 | T35: 0 | V35: 0.43696886 | W35: 0 | Y35: 0.43696886 | Z35: 0 | AB35: 0.43696886 | AC35: 0
I36: Row Labels | J36: Employees | L36: 31 | M36: 0.43114236 | N36: 0 | P36: 0.43114236 | Q36: 0 | S36: 0.43114236 | T36: 0 | V36: 0.43114236 | W36: 0 | Y36: 0.43114236 | Z36: 0 | AB36: 0.43114236 | AC36: 0
I37: UK | J37: 88 | L37: 32 | M37: 0.42780587 | N37: 1 | P37: 0.42780587 | Q37: 1 | S37: 0.42780587 | T37: 1 | V37: 0.42780587 | W37: 1 | Y37: 0.42780587 | Z37: 1 | AB37: 0.42780587 | AC37: 1
I38: US | J38: 60 | L38: 33 | M38: 0.42240782 | N38: 1 | P38: 0.42240782 | Q38: 1 | S38: 0.42240782 | T38: 1 | V38: 0.42240782 | W38: 1 | Y38: 0.42240782 | Z38: 1 | AB38: 0.42240782 | AC38: 1
I39: Canada | J39: 48 | L39: 34 | M39: 0.41836543 | N39: 0 | P39: 0.41836543 | Q39: 0 | S39: 0.41836543 | T39: 0 | V39: 0.41836543 | W39: 0 | Y39: 0.41836543 | Z39: 0 | AB39: 0.41836543 | AC39: 0
I40: Singapore | J40: 23 | L40: 35 | M40: 0.41327334 | N40: 1 | P40: 0.41327334 | Q40: 1 | S40: 0.41327334 | T40: 1 | V40: 0.41327334 | W40: 1 | Y40: 0.41327334 | Z40: 1 | AB40: 0.41327334 | AC40: 1
I41: Ireland | J41: 20 | L41: 36 | M41: 0.41148355 | N41: 0 | P41: 0.41148355 | Q41: 0 | S41: 0.41148355 | T41: 0 | V41: 0.41148355 | W41: 0 | Y41: 0.41148355 | Z41: 0 | AB41: 0.41148355 | AC41: 0
I42: Germany | J42: 11 | L42: 37 | M42: 0.41126199 | N42: 0 | P42: 0.41126199 | Q42: 0 | S42: 0.41126199 | T42: 0 | V42: 0.41126199 | W42: 0 | Y42: 0.41126199 | Z42: 0 | AB42: 0.41126199 | AC42: 0
I43: Grand Total | J43: 250 | L43: 38 | M43: 0.40706293 | N43: 0 | P43: 0.40706293 | Q43: 0 | S43: 0.40706293 | T43: 0 | V43: 0.40706293 | W43: 0 | Y43: 0.40706293 | Z43: 0 | AB43: 0.40706293 | AC43: 0
L44: 39 | M44: 0.40337419 | N44: 0 | P44: 0.40337419 | Q44: 0 | S44: 0.40337419 | T44: 0 | V44: 0.40337419 | W44: 0 | Y44: 0.40337419 | Z44: 0 | AB44: 0.40337419 | AC44: 0
L45: 40 | M45: 0.39984097 | N45: 0 | P45: 0.39984097 | Q45: 0 | S45: 0.39984097 | T45: 0 | V45: 0.39984097 | W45: 0 | Y45: 0.39984097 | Z45: 0 | AB45: 0.39984097 | AC45: 0
I46: Risk | J46: (Multiple Items) | L46: 41 | M46: 0.3956252 | N46: 1 | P46: 0.3956252 | Q46: 1 | S46: 0.3956252 | T46: 1 | V46: 0.3956252 | W46: 1 | Y46: 0.3956252 | Z46: 1 | AB46: 0.3956252 | AC46: 1
L47: 42 | M47: 0.39555228 | N47: 0 | P47: 0.39555228 | Q47: 0 | S47: 0.39555228 | T47: 0 | V47: 0.39555228 | W47: 0 | Y47: 0.39555228 | Z47: 0 | AB47: 0.39555228 | AC47: 0
I48: Row Labels | J48: Employees | L48: 43 | M48: 0.39413062 | N48: 1 | P48: 0.39413062 | Q48: 1 | S48: 0.39413062 | T48: 1 | V48: 0.39413062 | W48: 1 | Y48: 0.39413062 | Z48: 1 | AB48: 0.39413062 | AC48: 1
I49: Professional | J49: 85 | L49: 44 | M49: 0.38689127 | N49: 0 | P49: 0.38689127 | Q49: 0 | S49: 0.38689127 | T49: 0 | V49: 0.38689127 | W49: 0 | Y49: 0.38689127 | Z49: 0 | AB49: 0.38689127 | AC49: 0
I50: Entry | J50: 52 | L50: 45 | M50: 0.38593723 | N50: 1 | P50: 0.38593723 | Q50: 1 | S50: 0.38593723 | T50: 1 | V50: 0.38593723 | W50: 1 | Y50: 0.38593723 | Z50: 1 | AB50: 0.38593723 | AC50: 1
I51: Senior | J51: 50 | L51: 46 | M51: 0.38361206 | N51: 0 | P51: 0.38361206 | Q51: 0 | S51: 0.38361206 | T51: 0 | V51: 0.38361206 | W51: 0 | Y51: 0.38361206 | Z51: 0 | AB51: 0.38361206 | AC51: 0
I52: Manager | J52: 44 | L52: 47 | M52: 0.3827407 | N52: 0 | P52: 0.3827407 | Q52: 0 | S52: 0.3827407 | T52: 0 | V52: 0.3827407 | W52: 0 | Y52: 0.3827407 | Z52: 0 | AB52: 0.3827407 | AC52: 0
I53: Senior Manager | J53: 19 | L53: 48 | M53: 0.3807288 | N53: 1 | P53: 0.3807288 | Q53: 1 | S53: 0.3807288 | T53: 1 | V53: 0.3807288 | W53: 1 | Y53: 0.3807288 | Z53: 1 | AB53: 0.3807288 | AC53: 1
I54: Grand Total | J54: 250 | L54: 49 | M54: 0.37884347 | N54: 0 | P54: 0.37884347 | Q54: 0 | S54: 0.37884347 | T54: 0 | V54: 0.37884347 | W54: 0 | Y54: 0.37884347 | Z54: 0 | AB54: 0.37884347 | AC54: 0
L55: 50 | M55: 0.37870129 | N55: 0 | P55: 0.37870129 | Q55: 0 | S55: 0.37870129 | T55: 0 | V55: 0.37870129 | W55: 0 | Y55: 0.37870129 | Z55: 0 | AB55: 0.37870129 | AC55: 0
L56: 51 | M56: 0.37711417 | N56: 0 | P56: 0.37711417 | Q56: 0 | S56: 0.37711417 | T56: 0 | V56: 0.37711417 | W56: 0 | Y56: 0.37711417 | Z56: 0 | AB56: 0.37711417 | AC56: 0
L57: 52 | M57: 0.37470762 | N57: 0 | P57: 0.37470762 | Q57: 0 | S57: 0.37470762 | T57: 0 | V57: 0.37470762 | W57: 0 | Y57: 0.37470762 | Z57: 0 | AB57: 0.37470762 | AC57: 0
L58: 53 | M58: 0.37338808 | N58: 1 | P58: 0.37338808 | Q58: 1 | S58: 0.37338808 | T58: 1 | V58: 0.37338808 | W58: 1 | Y58: 0.37338808 | Z58: 1 | AB58: 0.37338808 | AC58: 1
L59: 54 | M59: 0.37329152 | N59: 1 | P59: 0.37329152 | Q59: 1 | S59: 0.37329152 | T59: 1 | V59: 0.37329152 | W59: 1 | Y59: 0.37329152 | Z59: 1 | AB59: 0.37329152 | AC59: 1
L60: 55 | M60: 0.3723963 | N60: 1 | P60: 0.3723963 | Q60: 1 | S60: 0.3723963 | T60: 1 | V60: 0.3723963 | W60: 1 | Y60: 0.3723963 | Z60: 1 | AB60: 0.3723963 | AC60: 1
L61: 56 | M61: 0.37029642 | N61: 0 | P61: 0.37029642 | Q61: 0 | S61: 0.37029642 | T61: 0 | V61: 0.37029642 | W61: 0 | Y61: 0.37029642 | Z61: 0 | AB61: 0.37029642 | AC61: 0
L62: 57 | M62: 0.36681663 | N62: 0 | P62: 0.36681663 | Q62: 0 | S62: 0.36681663 | T62: 0 | V62: 0.36681663 | W62: 0 | Y62: 0.36681663 | Z62: 0 | AB62: 0.36681663 | AC62: 0
L63: 58 | M63: 0.36582575 | N63: 1 | P63: 0.36582575 | Q63: 1 | S63: 0.36582575 | T63: 1 | V63: 0.36582575 | W63: 1 | Y63: 0.36582575 | Z63: 1 | AB63: 0.36582575 | AC63: 1
L64: 59 | M64: 0.36403752 | N64: 0 | P64: 0.36403752 | Q64: 0 | S64: 0.36403752 | T64: 0 | V64: 0.36403752 | W64: 0 | Y64: 0.36403752 | Z64: 0 | AB64: 0.36403752 | AC64: 0
L65: 60 | M65: 0.36400329 | N65: 1 | P65: 0.36400329 | Q65: 1 | S65: 0.36400329 | T65: 1 | V65: 0.36400329 | W65: 1 | Y65: 0.36400329 | Z65: 1 | AB65: 0.36400329 | AC65: 1
L66: 61 | M66: 0.36220884 | N66: 0 | P66: 0.36220884 | Q66: 0 | S66: 0.36220884 | T66: 0 | V66: 0.36220884 | W66: 0 | Y66: 0.36220884 | Z66: 0 | AB66: 0.36220884 | AC66: 0
... L105: 100 | M105: 0.30076002 | N105: 0 | P105: 0.30076002 | Q105: 0 | S105: 0.30076002 | T105: 0 | V105: 0.30076002 | W105: 0 | Y105: 0.30076002 | Z105: 0 | AB105: 0.30076002 | AC105: 0
L106: 101 | M106: 0.30073723 | N106: 1 | Q106: =SUM(Q6:Q105) -> 47 | S106: 0.30073723 | T106: 1 | V106: 0.30073723 | W106: 1 | Y106: 0.30073723 | Z106: 1 | AB106: 0.30073723 | AC106: 1
L107: 102 | M107: 0.30058022 | N107: 0 | Q107: =Q106/N1006 -> 0.31543624 | S107: 0.30058022 | T107: 0 | V107: 0.30058022 | W107: 0 | Y107: 0.30058022 | Z107: 0 | AB107: 0.30058022 | AC107: 0
L108: 103 | M108: 0.29934267 | N108: 0 | S108: 0.29934267 | T108: 0 | V108: 0.29934267 | W108: 0 | Y108: 0.29934267 | Z108: 0 | AB108: 0.29934267 | AC108: 0
L109: 104 | M109: 0.29840452 | N109: 1 | S109: 0.29840452 | T109: 1 | V109: 0.29840452 | W109: 1 | Y109: 0.29840452 | Z109: 1 | AB109: 0.29840452 | AC109: 1
L110: 105 | M110: 0.29831593 | N110: 0 | S110: 0.29831593 | T110: 0 | V110: 0.29831593 | W110: 0 | Y110: 0.29831593 | Z110: 0 | AB110: 0.29831593 | AC110: 0
L111: 106 | M111: 0.29650742 | N111: 1 | S111: 0.29650742 | T111: 1 | V111: 0.29650742 | W111: 1 | Y111: 0.29650742 | Z111: 1 | AB111: 0.29650742 | AC111: 1
L112: 107 | M112: 0.29631963 | N112: 0 | S112: 0.29631963 | T112: 0 | V112: 0.29631963 | W112: 0 | Y112: 0.29631963 | Z112: 0 | AB112: 0.29631963 | AC112: 0
L113: 108 | M113: 0.29384572 | N113: 1 | S113: 0.29384572 | T113: 1 | V113: 0.29384572 | W113: 1 | Y113: 0.29384572 | Z113: 1 | AB113: 0.29384572 | AC113: 1
L114: 109 | M114: 0.29163224 | N114: 1 | S114: 0.29163224 | T114: 1 | V114: 0.29163224 | W114: 1 | Y114: 0.29163224 | Z114: 1 | AB114: 0.29163224 | AC114: 1
L115: 110 | M115: 0.29065599 | N115: 0 | S115: 0.29065599 | T115: 0 | V115: 0.29065599 | W115: 0 | Y115: 0.29065599 | Z115: 0 | AB115: 0.29065599 | AC115: 0
L116: 111 | M116: 0.28821854 | N116: 0 | S116: 0.28821854 | T116: 0 | V116: 0.28821854 | W116: 0 | Y116: 0.28821854 | Z116: 0 | AB116: 0.28821854 | AC116: 0
L117: 112 | M117: 0.28785691 | N117: 0 | S117: 0.28785691 | T117: 0 | V117: 0.28785691 | W117: 0 | Y117: 0.28785691 | Z117: 0 | AB117: 0.28785691 | AC117: 0
L118: 113 | M118: 0.28772967 | N118: 1 | S118: 0.28772967 | T118: 1 | V118: 0.28772967 | W118: 1 | Y118: 0.28772967 | Z118: 1 | AB118: 0.28772967 | AC118: 1
L119: 114 | M119: 0.28557249 | N119: 0 | S119: 0.28557249 | T119: 0 | V119: 0.28557249 | W119: 0 | Y119: 0.28557249 | Z119: 0 | AB119: 0.28557249 | AC119: 0
... L205: 200 | M205: 0.22692148 | N205: 1 | S205: 0.22692148 | T205: 1 | V205: 0.22692148 | W205: 1 | Y205: 0.22692148 | Z205: 1 | AB205: 0.22692148 | AC205: 1
L206: 201 | M206: 0.22679339 | N206: 0 | T206: =SUM(T6:T205) -> 72 | V206: 0.22679339 | W206: 0 | Y206: 0.22679339 | Z206: 0 | AB206: 0.22679339 | AC206: 0
L207: 202 | M207: 0.22569388 | N207: 0 | T207: =T206/N1006 -> 0.48322148 | V207: 0.22569388 | W207: 0 | Y207: 0.22569388 | Z207: 0 | AB207: 0.22569388 | AC207: 0
L208: 203 | M208: 0.22561576 | N208: 0 | V208: 0.22561576 | W208: 0 | Y208: 0.22561576 | Z208: 0 | AB208: 0.22561576 | AC208: 0
L209: 204 | M209: 0.22465551 | N209: 1 | V209: 0.22465551 | W209: 1 | Y209: 0.22465551 | Z209: 1 | AB209: 0.22465551 | AC209: 1
L210: 205 | M210: 0.22389597 | N210: 0 | V210: 0.22389597 | W210: 0 | Y210: 0.22389597 | Z210: 0 | AB210: 0.22389597 | AC210: 0
L211: 206 | M211: 0.22365332 | N211: 0 | V211: 0.22365332 | W211: 0 | Y211: 0.22365332 | Z211: 0 | AB211: 0.22365332 | AC211: 0
L212: 207 | M212: 0.22331249 | N212: 0 | V212: 0.22331249 | W212: 0 | Y212: 0.22331249 | Z212: 0 | AB212: 0.22331249 | AC212: 0
L213: 208 | M213: 0.22217285 | N213: 0 | V213: 0.22217285 | W213: 0 | Y213: 0.22217285 | Z213: 0 | AB213: 0.22217285 | AC213: 0
L214: 209 | M214: 0.22145245 | N214: 0 | V214: 0.22145245 | W214: 0 | Y214: 0.22145245 | Z214: 0 | AB214: 0.22145245 | AC214: 0
L215: 210 | M215: 0.22118889 | N215: 0 | V215: 0.22118889 | W215: 0 | Y215: 0.22118889 | Z215: 0 | AB215: 0.22118889 | AC215: 0
L216: 211 | M216: 0.22042954 | N216: 0 | V216: 0.22042954 | W216: 0 | Y216: 0.22042954 | Z216: 0 | AB216: 0.22042954 | AC216: 0
L217: 212 | M217: 0.22039338 | N217: 0 | V217: 0.22039338 | W217: 0 | Y217: 0.22039338 | Z217: 0 | AB217: 0.22039338 | AC217: 0
L218: 213 | M218: 0.22013428 | N218: 0 | V218: 0.22013428 | W218: 0 | Y218: 0.22013428 | Z218: 0 | AB218: 0.22013428 | AC218: 0
L219: 214 | M219: 0.22005411 | N219: 0 | V219: 0.22005411 | W219: 0 | Y219: 0.22005411 | Z219: 0 | AB219: 0.22005411 | AC219: 0
... L305: 300 | M305: 0.17796285 | N305: 0 | V305: 0.17796285 | W305: 0 | Y305: 0.17796285 | Z305: 0 | AB305: 0.17796285 | AC305: 0
L306: 301 | M306: 0.17747963 | N306: 0 | W306: =SUM(W6:W305) -> 88 | Y306: 0.17747963 | Z306: 0 | AB306: 0.17747963 | AC306: 0
L307: 302 | M307: 0.1770337 | N307: 0 | W307: =W306/N1006 -> 0.59060403 | Y307: 0.1770337 | Z307: 0 | AB307: 0.1770337 | AC307: 0
L308: 303 | M308: 0.17654406 | N308: 0 | Y308: 0.17654406 | Z308: 0 | AB308: 0.17654406 | AC308: 0
L309: 304 | M309: 0.17619619 | N309: 0 | Y309: 0.17619619 | Z309: 0 | AB309: 0.17619619 | AC309: 0
L310: 305 | M310: 0.17548144 | N310: 0 | Y310: 0.17548144 | Z310: 0 | AB310: 0.17548144 | AC310: 0
...

Sheet Launch of Risk Calculator
A1: Subject: Launch: Data-Driven Attrition Risk Calculator & User Guide
A2: Team,
A3: As part of our commitment to proactive talent management, we are officially launching our new Data-Driven Attrition Risk Calculator.
A4: Built directly within Excel using historical company data, this tool moves us away from guesswork. It allows HR Business Partners to input an employee’s profile and instantly generate an individual 0% to 100% Flight Risk Probability Score.
A5: The calculator tab is now active in our workforce planning file. Please review the simple user guide below to ensure your evaluations are mathematically accurate.
A7: 📊 Attrition Risk Calculator: Manager User Guide
A8: This interactive tool uses our verified predictive model (Brier Score: 0.11272) to estimate an employee's flight risk relative to our company baseline turnover rate of 15%. Use this data to drive proactive career conversations and targeted retention efforts.
A9: 🛠️ How to Input Employee Data
A10: 1. Numeric Fields: Enter exact values in the input column. Keep values realistic (e.g., Compa-Ratio as a decimal like 0.95, Age between 18 and 100).
A11: 2. Dropdown Selectors: Choose the single matching option for Department, Country, Performance, Job Level, and Work Setup.
A12: 3. Security Notice: All mathematical weight matrices and conversion formulas are permanently locked. You only need to modify the open input blocks.
A13: 🚨 Interpreting the Risk Tiers & Strategic Actions
... A35: Workforce Analytics & HR Strategy

Sheet Live Individual Calculator 
A1: *Enter a 1 (Yes) or 0 (No) for the binary encoded rows based on your exact definitions (e.g., if they work overtime, enter 1 because No Overtime = 0), ( if no promotion, enter 0 because Promotion = 1).
E2: =EXP(SUMPRODUCT(B5:B38, C5:C38)) / (1 + EXP(SUMPRODUCT(B5:B38, C5:C38))) -> 0.74846182
A4: Variables | B4: Weights | C4: Math Bridge | D4: Manager Interaction Input Zone | E4: =IF(E2 > 0.3, "🚨 HIGH RISK: Strategic Stay-Interview", IF(E2 > 0.1, "⚠️ MEDIUM RISK: Manager Check-in", "✅ LOW RISK: Standard Retention")) -> 🚨 HIGH RISK: Strategic Stay-Interview
A5: Intercept | B5: -0.87567091 | C5: 1
A6: Age | B6: -0.0096127547 | C6: =D6 -> 32 | D6: 32 | E6: Select Department | F6: Operations
A7: Tenure (Years) | B7: -0.071322781 | C7: =D7 -> 1 | D7: 1 | E7: Select Country | F7: Canada
A8: Time in Role (Years) | B8: 0.21601685 | C8: =D8 -> 1 | D8: 1 | E8: Select Performance Tier | F8: Needs Improvement
A9: Compa-Ratio | B9: 0.29290994 | C9: =D9 -> 0.85 | D9: 0.85 | E9: Select Job Level | F9: Entry
A10: Promotion in Last 2 Years | B10: 0.7957323 | C10: =IF(D10="No",1,0) -> 1 | D10: No | E10: Select Work Setup | F10: Office
A11: Months Since Salary Increase | B11: 0.020052706 | C11: =D11 -> 18 | D11: 18
A12: Engagement Score | B12: -0.033631459 | C12: =D12 -> 2 | D12: 2
A13: Absence Days | B13: 0.01834052 | C13: =D13 -> 12 | D13: 12
A14: Manager Tenure (Years) | B14: 0.031426791 | C14: =D14 -> 1 | D14: 1
A15: Overtime | B15: -0.57903445 | C15: =IF(D15="Yes", 0, 1) -> 0 | D15: Yes
A16: Training Hours | B16: 0.0054640706 | C16: =D16 -> 10 | D16: 10
A17: Gender_Female | B17: 0.4844651 | C17: =IF(D17="Female", 1, 0) -> 1 | D17: Female
A18: Perf_Needs_Improvement | B18: 0.12909761 | C18: =IF($F$8="Yes", 1, 0) -> 0
A19: Perf_Exceeds | B19: -0.081116629 | C19: =IF($F$8="Yes", 1, 0) -> 0
A20: Perf_Outstanding | B20: -0.23588423 | C20: =IF($F$8="Yes", 1, 0) -> 0
A21: Job_Entry | B21: 0.41391554 | C21: =IF($F$9="Yes", 1, 0) -> 0
A22: Job_Manager | B22: 0.15038906 | C22: =IF($F$9="Yes", 1, 0) -> 0
A23: Job_Senior | B23: -0.28926721 | C23: =IF($F$9="Yes", 1, 0) -> 0
A24: Job_Senior_Manager | B24: 0.088629935 | C24: =IF($F$9="Yes", 1, 0) -> 0
A25: Dept_Claims | B25: 0.066576659 | C25: =IF($F$6="Yes", 1, 0) -> 0
A26: Dept_Finance | B26: 0.052375185 | C26: =IF($F$6="Finance", 1, 0) -> 0
A27: Dept_HR | B27: 0.13098757 | C27: =IF($F$6="Yes", 1, 0) -> 0
A28: Dept_IT | B28: 0.087598149 | C28: =IF($F$6="Yes", 1, 0) -> 0
A29: Dept_Marketing | B29: -0.14789576 | C29: =IF($F$6="Yes", 1, 0) -> 0
A30: Dept_Sales | B30: 0.072181123 | C30: =IF($F$6="Yes", 1, 0) -> 0
A31: Dept_Underwriting | B31: -0.42022541 | C31: =IF($F$6="Yes", 1, 0) -> 0
A32: Country_Canada | B32: 1.0586403 | C32: =IF($F$7="Yes", 1, 0) -> 0
A33: Country_Germany | B33: 0.16068222 | C33: =IF($F$7="Yes", 1, 0) -> 0
A34: Country_Ireland | B34: 0.85182842 | C34: =IF($F$7="Yes", 1, 0) -> 0
A35: Country_Singapore | B35: 0.38441114 | C35: =IF($F$7="Yes", 1, 0) -> 0
A36: Country_US | B36: 0.12074148 | C36: =IF($F$7="Yes", 1, 0) -> 0
A37: Work_Office | B37: 0.0082859418 | C37: =IF($F$11="Yes", 1, 0) -> 0
A38: Work_Remote | B38: 0.0014628186 | C38: =IF($F$11="Yes", 1, 0) -> 0
A45: 🎛️ Creating the Live Individual Calculator Tab
A46: To make this user-friendly for managers, create a new tab in your Excel file laid out exactly like this.
A47: Layout Structure:
A48: Column A (Variables): List all your variables vertically starting at row 5 (A5: Intercept, A6: Age, A7: Tenure, etc.).
A49: Column B (Weights): Paste your permanent, optimized coefficients right next to them (B5: -0.88, B6: -0.01, B7: -0.07, etc.).
A50: Column C (User Input): This is where managers enter data for a specific employee.
A51: Put a permanent 1 in cell C5 for the Intercept.
A52: Enter raw numbers for numeric rows (e.g., Age: 34, Tenure: 3).
A53: Enter a 1 (Yes) or 0 (No) for the binary encoded rows based on your exact definitions (e.g., if they work overtime, enter 0 because No Overtime = 1).
A54: The Output Matrix:
A55: At the very top of the sheet, merge cells E2:F3, color it light blue, and enter this exact formula to display the live probability score:
A56: excel
A57: =EXP(SUMPRODUCT('Dashboard 4_Predictive Attritio'!A15:A53, 'Dashboard 4_Predictive Attritio'!B15:B48)) / (1 + EXP(SUMPRODUCT('Dashboard 4_Predictive Attritio'!A15:A51, 'Dashboard 4_Predictive Attritio'!B15:B48))) -> #VALUE!
A58: Use code with caution.
A59: Format this cell as a Percentage (%) with large, bold text. When values in Column C change, this percentage will instantly update.

Sheet Insights & Takeaways
A1: Key findings
A3: 1. Department
A5: IT contributes the largest proportion of leavers (17%), followed by Sales and Operations (16% each).
A6: However, Finance has the highest departmental attrition rate at 18%, followed by HR (16.3%) and Claims (16.1%).
A7: This indicates that the volume of leavers and the rate of attrition tell different stories, with Finance warranting particular attention.
A9: 2. Age
A11: Employees aged 32–45 account for 60% of all leavers, making this the largest leaver population.
A12: Their attrition rate is 16.2%.
A13: The 60–73 group has a high apparent attrition rate of 50%, but represents only 1% of leavers, so this should be treated cautiously because of the small population.
A15: 3. Gender
A17: Males represent 58% of leavers, compared with 42% females.
A18: However, the female attrition rate is 17.3%, compared with 12.5% for males.
... A45: The descriptive analysis indicates an overall attrition rate of 14.9%, with 149 leavers averaging 4.5 years' tenure. While IT contributes the largest proportion of leavers, Finance has the highest departmental attrition rate. Attrition also appears elevated among female employees, early-tenure employees, entry-level employees and employees in Canada. The analysis highlights a number of populations that warrant further investigation, particularly where high attrition rates are not reflected in the overall volume of leavers.

Sheet Executive Insights & Recommenda
A1: Executive summary
A3: Overall attrition is 14.9%, with 149 leavers from a workforce of 1,000. Attrition is concentrated in specific workforce populations rather than being evenly distributed. The analysis identifies engagement, reward positioning and time since salary increase as recurring factors associated with higher attrition.
A8: Area | B8: Key Finding | C8: Attrition
A9: Engagaement | B9: Low engagement employees have significantly higher attrition | C9: 0.38
A10: Reward Positioning | B10: Employees with compa-ratio <0.85 show elevated attrition | C10: 0.22
A11: Salary Progression | B11: Employees with 24+ months since salary increase show elevated attrition | C11: 0.24
A12: Promotion | B12: Employees without promotion have higher attrition | C12: 18% vs 8%
A15: Where is attrition concentrated?
A16: Population | B16: Attrition | C16: Overall | D16: Difference
A17: Canada | B17: 0.28 | C17: 0.149 | D17: +13.1pp
A18: Entry level | B18: 0.21 | C18: 0.149 | D18: +6.1pp
A19: Finance | B19: 0.18 | C19: 0.149 | D19: +3.1pp
A20: Female | B20: 0.173 | C20: 0.149 | D20: +2.4pp
A21: HR | B21: 0.163 | C21: 0.149 | D21: +1.4pp
A22: Claims | B22: 0.161 | C22: 0.149 | D22: +1.2pp
A25: Diagnostic findings
A27: Potential drivers / associated factors
A29: Engagement - Low-engagement employees have an attrition rate of 38%, compared with 10% among very-high engagement employees.
A33: Reward - Employees with a compa-ratio below 0.85 have 22% attrition, compared with 13% for employees at 0.85–<1.00.
A37: Salary progression - Employees who have gone 24+ months since their last salary increase have 24% attrition, compared with 12% among those receiving an increase within 6–12 months.
A41: Promotion - Employees who have not received a promotion have 18% attrition, compared with 8% among employees who have received one.
A45: Overtime - Employees working overtime have 21% attrition, compared with 12% among employees who do not.
A49: Intersection analysis
A51: Finance
A52: Finance has 18% overall attrition.
A53: Low engagement → 57%
A54: Compa-ratio <0.85 → 54%
... A82: Recommendations
A83: Finding | B83: Recommended action
A84: Low engagement associated with high attrition | B84: Conduct targeted engagement analysis and focus groups to understand key drivers
A85: Low compa-ratio associated with higher attrition | B85: Review compensation positioning and market competitiveness for high-risk populations
A86: 24+ months since salary increase | B86: Review salary progression and pay-review history for affected employees
A87: Entry-level attrition elevated | B87: Review early-career development, progression and reward pathways
A88: Finance attrition elevated | B88: Conduct deeper Finance workforce review
A89: Female attrition higher | B89: Investigate progression, reward positioning and engagement by gender
A90: Canada attrition significantly elevated | B90: Conduct country-level workforce review to identify local drivers
A93: Limitations
A94: Analytical considerations
A95: The analysis identifies patterns and associations within the workforce data but does not establish causation. Some segments contain relatively small populations, meaning high attrition percentages should be interpreted cautiously. Further analysis, including statistical testing, qualitative feedback and stakeholder validation, would help confirm the underlying drivers of attrition.
A99: INSIGHTS
A103: Executive Summary: Data-Driven Employee Attrition Insights
A104: This analysis leverages a trained Logistic Regression model to isolate the structural, geographic, and behavioral levers driving employee turnover. By evaluating historical records, the model calculates individual risk probabilities and uncovers the specific factors that either increase attrition risk or serve as strong retention anchors.
A107: All insights below are measured relative to the baseline reference group: Male employees based in the UK, working in the Operations department, holding a mid-level Professional role, who met performance expectations under a Hybrid working arrangement.
A112: 📊 Top Turn-Over Drivers (High Risk Factors)
A113: Geographic Variances (Canada & Ireland): Employees based in Canada (+1.06) and Ireland (+0.85) exhibit a drastically higher turnover risk compared to their peers in the baseline region (UK).
A114: Career Stagnation (No Promotion): Having no promotion in the last 2 years (+0.80) carries an heavily elevated risk of leaving. Stagnant upward mobility serves as a top push-factor within this corporate framework.
A115: Burnout Metrics (Overtime): Working active Overtime (+0.58) introduces a substantial risk penalty to an employee's profile, making them significantly more volatile due to workload pressures.
A116: Gender Disparity: Female employees (+0.48) show a notably higher risk profile than male employees within this dataset, suggesting a need to evaluate internal equity, inclusion, or support systems.
... A134: 3. Burnout Mitigation: Audit teams logging heavy Overtime (+0.58) hours. Actively deploy workload redistribution strategies to transition stressed employees back into standard, predictable baseline schedule hours.

Sheet Diagnostic Analysis
A2: Overall diagnostic factors | N2: Attrition | O2: Yes | S2: Attrition | T2: Yes
A4: Engagement score | B4: Employee | C4: Leavers | D4: Attrition % | F4: Attrition is substantially higher among employees with lower engagement scores, reaching 38% among the Low engagement group compared with 10% among Very High engagement employees. This suggests engagement may be an important factor associated with employee retention and warrants further investigation. | N4: Department | O4: No of Leavers | S4: No of Leavers | T4: Column Labels
A5: High | B5: 417 | C5: 48 | D5: 0.11510791 | N5: Entry | O5: 0.17449664 | S5: Department | T5: Less than 1 year | U5: 1-<2 years | V5: 2-<5 years | W5: 5-<10 years | X5: 10-<15 years | Y5: Grand Total
A6: Low | B6: 40 | C6: 15 | D6: 0.375 | N6: Manager | O6: 0.15436242 | S6: Entry | T6: 0.0067114094 | U6: 0.033557047 | V6: 0.080536913 | W6: 0.053691275 | X6: 0 | Y6: 0.17449664
A7: Moderate | B7: 408 | C7: 73 | D7: 0.17892157 | N7: Professional | O7: 0.3557047 | S7: Manager | T7: 0.0067114094 | U7: 0.020134228 | V7: 0.033557047 | W7: 0.080536913 | X7: 0.013422819 | Y7: 0.15436242
A8: Very high | B8: 135 | C8: 13 | D8: 0.096296296 | N8: Senior | O8: 0.24161074 | S8: Professional | T8: 0.020134228 | U8: 0.040268456 | V8: 0.19463087 | W8: 0.087248322 | X8: 0.013422819 | Y8: 0.3557047
A9: Grand Total | B9: 1000 | C9: 149 | D9: 0.149 | N9: Senior Manager | O9: 0.073825503 | S9: Senior | T9: 0.026845638 | U9: 0.013422819 | V9: 0.10067114 | W9: 0.087248322 | X9: 0.013422819 | Y9: 0.24161074
N10: Grand Total | O10: 1 | S10: Senior Manager | T10: 0.0067114094 | U10: 0.013422819 | V10: 0.033557047 | W10: 0.020134228 | X10: 0 | Y10: 0.073825503
S11: Grand Total | T11: 0.067114094 | U11: 0.12080537 | V11: 0.44295302 | W11: 0.32885906 | X11: 0.040268456 | Y11: 1
A13: Compa ratio | B13: Employee | C13: Leavers | D13: Attrition % | F13: Attrition is highest among employees with a compa-ratio below 0.85 (22%), but is also elevated among employees at 1.15+ (19%), suggesting a non-linear relationship between compensation positioning and attrition that warrants further investigation.
A14: 0.85-<1.00 | B14: 412 | C14: 54 | D14: 0.13106796
A15: 1.00-<1.15 | B15: 395 | C15: 56 | D15: 0.14177215 | N15: Attrition | O15: Yes
A16: 1.15+ | B16: 102 | C16: 19 | D16: 0.18627451
A17: less than 0.85 | B17: 91 | C17: 20 | D17: 0.21978022 | N17: Department | O17: No of Leavers
A18: Grand Total | B18: 1000 | C18: 149 | D18: 0.149 | N18: 1-<2 years | O18: 0.12080537
N19: Sales | O19: 0.033557047
N20: IT | O20: 0.026845638
N21: Finance | O21: 0.020134228
A22: Salary increase recency | B22: Employee | C22: Leavers | D22: Attrition % | F22: Employees who have gone 24 months or more since their last salary increase have the highest attrition rate at 24%, compared with 12–14% among employees whose last increase occurred within the previous 24 months. This suggests salary increase recency may be associated with retention. | N22: Operations | O22: 0.020134228
A23: <6 months | B23: 118 | C23: 16 | D23: 0.13559322 | N23: HR | O23: 0.0067114094
A24: 13-24 months | B24: 496 | C24: 65 | D24: 0.13104839 | N24: Underwriting | O24: 0.0067114094
A25: 24+ months | B25: 173 | C25: 42 | D25: 0.24277457 | N25: Claims | O25: 0.0067114094
A26: 6-12 months | B26: 213 | C26: 26 | D26: 0.12206573 | N26: 10-<15 years | O26: 0.040268456
A27: Grand Total | B27: 1000 | C27: 149 | D27: 0.149 | N27: Sales | O27: 0.013422819
N28: Claims | O28: 0.013422819
N29: Operations | O29: 0.0067114094
N30: HR | O30: 0.0067114094
A31: Promotion | B31: Employee | C31: Leavers | D31: Attrition % | F31: Employees who had not received a promotion had an attrition rate of 18%, compared with 8% among employees who had been promoted. This indicates a strong association between recent promotion status and retention, although further analysis would be required to understand the underlying drivers. | N31: 2-<5 years | O31: 0.44295302
A32: No | B32: 719 | C32: 127 | D32: 0.17663421 | N32: IT | O32: 0.073825503
A33: Yes | B33: 281 | C33: 22 | D33: 0.078291815 | N33: Sales | O33: 0.060402685
A34: Grand Total | B34: 1000 | C34: 149 | D34: 0.149 | N34: Finance | O34: 0.053691275
N35: Operations | O35: 0.053691275
N36: HR | O36: 0.053691275
N37: Claims | O37: 0.053691275
A38: Performance | B38: Employee | C38: Leavers | D38: Attrition % | F38: Attrition varies relatively little across performance categories, ranging from 13% among Outstanding performers to 17% among employees rated Needs Improvement. Performance therefore does not appear to be a major differentiator of attrition in this analysis. | N38: Underwriting | O38: 0.046979866
A39: Exceeds Expectations | B39: 282 | C39: 41 | D39: 0.14539007 | N39: Marketing | O39: 0.046979866
A40: Meets Expectations | B40: 567 | C40: 86 | D40: 0.15167549 | N40: 5-<10 years | O40: 0.32885906
A41: Needs Improvement | B41: 72 | C41: 12 | D41: 0.16666667 | N41: Finance | O41: 0.080536913
A42: Outstanding | B42: 79 | C42: 10 | D42: 0.12658228 | N42: Operations | O42: 0.067114094
A43: Grand Total | B43: 1000 | C43: 149 | D43: 0.149 | N43: Claims | O43: 0.053691275
N44: Sales | O44: 0.046979866
N45: IT | O45: 0.046979866
N46: HR | O46: 0.020134228
A47: Overtime | B47: Employee | C47: Leavers | D47: Attrition % | F47: Employees working overtime have an attrition rate of 21%, compared with 12% among employees who do not work overtime. This suggests a potentially important relationship between workload and retention that warrants further investigation. | N47: Underwriting | O47: 0.0067114094
A48: No | B48: 701 | C48: 87 | D48: 0.12410842 | N48: Marketing | O48: 0.0067114094
A49: Yes | B49: 299 | C49: 62 | D49: 0.20735786 | N49: Less than 1 year | O49: 0.067114094
A50: Grand Total | B50: 1000 | C50: 149 | D50: 0.149 | N50: IT | O50: 0.020134228
N51: Operations | O51: 0.013422819
N52: Underwriting | O52: 0.013422819
N53: Sales | O53: 0.0067114094
N54: Claims | O54: 0.0067114094
A55: Priority population analysis | N55: Marketing | O55: 0.0067114094
A56: Department | B56: Finance | N56: Grand Total | O56: 1
A58: Engagement band | B58: Employee | C58: Leavers | D58: Attrition % | F58: Finance overall has 18% attrition, compared with 14.9% overall. The 54% attrition among Finance employees below 0.85 compa-ratio is particularly striking.
A59: High | B59: 51 | C59: 7 | D59: 0.1372549
A60: Low | B60: 7 | C60: 4 | D60: 0.57142857
A61: Moderate | B61: 57 | C61: 12 | D61: 0.21052632 | F61: However, there are only 13 employees in that group, with 7 leavers, so I'd describe this as a high-risk indicator requiring further investigation, rather than concluding that low pay positioning causes attrition.
A62: Very high | B62: 13 | C62: 0 | D62: 0
A63: Grand Total | B63: 128 | C63: 23 | D63: 0.1796875
A67: Department | B67: Finance
A69: Salary increase recency | B69: Employee | C69: Leavers | D69: Attrition %
A70: <6 months | B70: 11 | C70: 2 | D70: 0.18181818
A71: 13-24 months | B71: 62 | C71: 10 | D71: 0.16129032
A72: 24+ months | B72: 26 | C72: 8 | D72: 0.30769231
A73: 6-12 months | B73: 29 | C73: 3 | D73: 0.10344828
A74: Grand Total | B74: 128 | C74: 23 | D74: 0.1796875
A78: Department | B78: Finance
A80: Compa-ratio | B80: Employee | C80: Leavers | D80: Attrition %
A81: 0.85-<1.00 | B81: 52 | C81: 6 | D81: 0.11538462
A82: 1.00-<1.15 | B82: 45 | C82: 9 | D82: 0.2
A83: 1.15+ | B83: 18 | C83: 1 | D83: 0.055555556
A84: less than 0.85 | B84: 13 | C84: 7 | D84: 0.53846154
A85: Grand Total | B85: 128 | C85: 23 | D85: 0.1796875
A89: Department | B89: Finance
A91: Promotion | B91: Employee | C91: Leavers | D91: Attrition %
A92: No | B92: 92 | C92: 18 | D92: 0.19565217
A93: Yes | B93: 36 | C93: 5 | D93: 0.13888889
A94: Grand Total | B94: 128 | C94: 23 | D94: 0.1796875
A98: Job Level | B98: Entry
A100: Engagement band | B100: Employee | C100: Leavers | D100: Attrition % | F100: Entry-level employees have 21% attrition, versus 14.9% overall. Entry-level employees who have gone 24+ months without a salary increase show materially higher attrition (48%), suggesting a potential relationship between reward progression and retention.
A101: High | B101: 53 | C101: 10 | D101: 0.18867925
A102: Low | B102: 9 | C102: 3 | D102: 0.33333333
A103: Moderate | B103: 46 | C103: 13 | D103: 0.2826087
A104: Very high | B104: 16 | C104: 0 | D104: 0
A105: Grand Total | B105: 124 | C105: 26 | D105: 0.20967742
A109: Job Level | B109: Entry
A111: Salary increase recency | B111: Employee | C111: Leavers | D111: Attrition %
A112: <6 months | B112: 19 | C112: 3 | D112: 0.15789474
A113: 13-24 months | B113: 60 | C113: 10 | D113: 0.16666667
A114: 24+ months | B114: 23 | C114: 11 | D114: 0.47826087
A115: 6-12 months | B115: 22 | C115: 2 | D115: 0.090909091
A116: Grand Total | B116: 124 | C116: 26 | D116: 0.20967742
A120: Job Level | B120: Entry
A122: Promotion | B122: Employee | C122: Leavers | D122: Attrition %
A123: No | B123: 89 | C123: 19 | D123: 0.21348315
A124: Yes | B124: 35 | C124: 7 | D124: 0.2
A125: Grand Total | B125: 124 | C125: 26 | D125: 0.20967742
A129: Job Level | B129: Entry
A131: Overtime | B131: Employee | C131: Leavers | D131: Attrition %
A132: No | B132: 87 | C132: 17 | D132: 0.1954023
...

Sheet Analytical Pivots
A1: LEAVERS PROFILE
A3: Row Labels | B3: Headcount | D3: Attrition | E3: Yes | H3: Attrition | I3: No
A4: No | B4: 851
A5: Grand Total | B5: 851 | D5: Average of Tenure (Years) | H5: Row Labels | I5: Headcount
D6: 4.5073826 | H6: Female | I6: 0.49001175
H7: Male | I7: 0.50998825
E8: Attrition | F8: Yes | H8: Grand Total | I8: 1
A9: Attrition | B9: No of Leavers
A10: Yes | B10: 149 | E10: No of Leavers | F10: Average of Tenure (Years)
A11: Grand Total | B11: 149 | E11: Female | F11: 4.3689655
E12: Male | F12: 4.7016129 | H12: Attrition | I12: Yes
E13: Grand Total | F13: 4.5073826
A14: No of Leavers | B14: No of Employees | C14: Count of Employee ID | H14: Attrition | I14: No of Leavers
A15: No | B15: 851 | C15: 0.851 | H15: Female | I15: 0.58389262
A16: Yes | B16: 149 | C16: 0.149 | H16: Male | I16: 0.41610738
A17: Grand Total | B17: 1000 | C17: 1 | H17: Grand Total | I17: 1
A19: Attrition | B19: Yes
A21: Department | B21: No of Leavers
A22: IT | B22: 0.16778523
A23: Sales | B23: 0.16107383
A24: Operations | B24: 0.16107383
A25: Finance | B25: 0.15436242
A26: Claims | B26: 0.13422819
A27: HR | B27: 0.087248322
A28: Underwriting | B28: 0.073825503
A29: Marketing | B29: 0.060402685
A30: Grand Total | B30: 1
A35: Attrition | B35: Yes
A37: Business Unit | B37: No of Leavers | C37: %
A38: Commercial | B38: 33 | C38: 0.22147651
A39: Corporate | B39: 23 | C39: 0.15436242
A40: Insurance | B40: 31 | C40: 0.20805369
A41: Operations | B41: 24 | C41: 0.16107383
A42: People | B42: 13 | C42: 0.087248322
A43: Technology | B43: 25 | C43: 0.16778523
A44: Grand Total | B44: 149 | C44: 1
A49: Attrition | B49: Yes
A51: Country | B51: No of Leavers | C51: %
A52: Canada | B52: 21 | C52: 0.1409396
A53: Germany | B53: 8 | C53: 0.053691275
A54: Ireland | B54: 10 | C54: 0.067114094
A55: Singapore | B55: 13 | C55: 0.087248322
A56: UK | B56: 60 | C56: 0.40268456
A57: US | B57: 37 | C57: 0.24832215
A58: Grand Total | B58: 149 | C58: 1
A62: Attrition | B62: Yes
A64: Job Level | B64: No of Employees
A65: Professional | B65: 0.3557047
A66: Senior | B66: 0.24161074
A67: Entry | B67: 0.17449664
A68: Manager | B68: 0.15436242
A69: Senior Manager | B69: 0.073825503
A70: Grand Total | B70: 1
D72: Attrition | E72: Yes | G72: Attrition | H72: Yes
A74: Attrition | B74: Yes | D74: Promotion | E74: No of Employees | G74: Working Arrangement | H74: No of Employees
D75: No | E75: 0.85234899 | G75: Hybrid | H75: 0.61073826
A76: Age group | B76: No of Employees | D76: Yes | E76: 0.14765101 | G76: Office | H76: 0.20134228
A77: 32-45 | B77: 0.59731544 | D77: Grand Total | E77: 1 | G77: Remote | H77: 0.18791946
A78: 18-31 | B78: 0.22818792 | G78: Grand Total | H78: 1
A79: 46-59 | B79: 0.16778523
A80: 60-73 | B80: 0.0067114094
A81: Grand Total | B81: 1
A85: Attrition | B85: Yes | D85: Attrition | E85: Yes
A87: Tenure Band | B87: No of Employees | D87: Performance Ratings | E87: No of Employees
A88: 2-<5 years | B88: 0.44295302 | D88: Exceeds Expectations | E88: 0.27516779
A89: 5-<10 years | B89: 0.32885906 | D89: Meets Expectations | E89: 0.57718121
A90: 1-<2 years | B90: 0.12080537 | D90: Needs Improvement | E90: 0.080536913
A91: Less than 1 year | B91: 0.067114094 | D91: Outstanding | E91: 0.067114094
A92: 10-<15 years | B92: 0.040268456 | D92: Grand Total | E92: 1
A93: Grand Total | B93: 1
A96: ATTRITION ANALYTICS
A98: Department | B98: Employees | C98: Leavers | D98: Attrition Rate
A99: Finance | B99: 128 | C99: 23 | D99: 0.1796875
A100: HR | B100: 80 | C100: 13 | D100: 0.1625
A101: Claims | B101: 124 | C101: 20 | D101: 0.16129032
A102: IT | B102: 157 | C102: 25 | D102: 0.15923567
A103: Sales | B103: 160 | C103: 24 | D103: 0.15
A104: Operations | B104: 163 | C104: 24 | D104: 0.14723926
A105: Marketing | B105: 77 | C105: 9 | D105: 0.11688312
A106: Underwriting | B106: 111 | C106: 11 | D106: 0.099099099
A107: Grand Total | B107: 1000 | C107: 149 | D107: 0.149
A110: Gender | B110: Employees | C110: Leavers | D110: Attrition Rate
A111: Female | B111: 504 | C111: 87 | D111: 0.17261905
A112: Male | B112: 496 | C112: 62 | D112: 0.125
A113: Grand Total | B113: 1000 | C113: 149 | D113: 0.149
A117: Age group | B117: Employees | C117: Leavers | D117: Attrition Rate
A118: 18-31 | B118: 245 | C118: 34 | D118: 0.13877551
A119: 32-45 | B119: 548 | C119: 89 | D119: 0.16240876
A120: 46-59 | B120: 205 | C120: 25 | D120: 0.12195122
A121: 60-73 | B121: 2 | C121: 1 | D121: 0.5
A122: Grand Total | B122: 1000 | C122: 149 | D122: 0.149
A126: Tenure Band | B126: Employees | C126: Leavers | D126: Attrition Rate
A127: 1-<2 years | B127: 136 | C127: 18 | D127: 0.13235294
A128: 10-<15 years | B128: 62 | C128: 6 | D128: 0.096774194
A129: 16+ years | B129: 6 | C129: 0 | D129: 0
A130: 2-<5 years | B130: 418 | C130: 66 | D130: 0.15789474
A131: 5-<10 years | B131: 325 | C131: 49 | D131: 0.15076923
A132: Less than 1 year | B132: 53 | C132: 10 | D132: 0.18867925
A133: Grand Total | B133: 1000 | C133: 149 | D133: 0.149
A137: Job level | B137: Employees | C137: Leavers | D137: Attrition Rate
...

Sheet Diagonistic Pivots
A1: Engagement score | B1: Attrition %
A2: Low | B2: 0.375
A3: Moderate | B3: 0.17892157
A4: High | B4: 0.11510791
A5: Very high | B5: 0.096296296
A6: Grand Total | B6: 0.149
A11: Employee | B11: Column Labels
A12: Engagement score | B12: Stayers | C12: Leavers
A13: High | B13: 369 | C13: 48
A14: Low | B14: 25 | C14: 15
A15: Moderate | B15: 335 | C15: 73
A16: Very high | B16: 122 | C16: 13
A17: Grand Total | B17: 851 | C17: 149
A24: Compa-ratio | B24: Attrition %
A25: less than 0.85 | B25: 0.21978022
A26: 1.15+ | B26: 0.18627451
A27: 1.00-<1.15 | B27: 0.14177215
A28: 0.85-<1.00 | B28: 0.13106796
A29: Grand Total | B29: 0.149
A33: Salary recency increase | B33: Attrition %
A34: 24+ months | B34: 0.24277457
A35: <6 months | B35: 0.13559322
A36: 13-24 months | B36: 0.13104839
A37: 6-12 months | B37: 0.12206573
A38: Grand Total | B38: 0.149
A41: Promotion | B41: Attrition %
A42: No | B42: 0.17663421
A43: Yes | B43: 0.078291815
A44: Grand Total | B44: 0.149
A48: Performance ratings | B48: Attrition %
A49: Needs Improvement | B49: 0.16666667
A50: Meets Expectations | B50: 0.15167549
A51: Exceeds Expectations | B51: 0.14539007
A52: Outstanding | B52: 0.12658228
A53: Grand Total | B53: 0.149
A56: Overtime | B56: Attrition %
A57: Yes | B57: 0.20735786
A58: No | B58: 0.12410842
A59: Grand Total | B59: 0.149

Sheet Dashboard Pivots
A1: LEAVERS PROFILE
A3: Row Labels | B3: Headcount | D3: Attrition | E3: Yes | H3: Attrition | I3: No
A4: No | B4: 851
A5: Grand Total | B5: 851 | D5: Average of Tenure (Years) | H5: Row Labels | I5: Headcount
D6: 4.5073826 | H6: Female | I6: 0.49001175
H7: Male | I7: 0.50998825
E8: Attrition | F8: Yes | H8: Grand Total | I8: 1
A9: Attrition | B9: No of Leavers
A10: Yes | B10: 149 | E10: No of Leavers | F10: Average of Tenure (Years)
A11: Grand Total | B11: 149 | E11: Female | F11: 4.3689655
E12: Male | F12: 4.7016129 | H12: Attrition | I12: Yes
E13: Grand Total | F13: 4.5073826
A14: No of Leavers | B14: No of Employees | C14: Count of Employee ID | H14: Attrition | I14: No of Leavers
A15: No | B15: 851 | C15: 0.851 | H15: Female | I15: 0.58389262
A16: Yes | B16: 149 | C16: 0.149 | H16: Male | I16: 0.41610738
A17: Grand Total | B17: 1000 | C17: 1 | H17: Grand Total | I17: 1
A19: Attrition | B19: Yes
A21: Department | B21: No of Leavers
A22: IT | B22: 0.16778523
A23: Sales | B23: 0.16107383
A24: Operations | B24: 0.16107383
A25: Finance | B25: 0.15436242
A26: Claims | B26: 0.13422819
A27: HR | B27: 0.087248322
A28: Underwriting | B28: 0.073825503
A29: Marketing | B29: 0.060402685
A30: Grand Total | B30: 1
A35: Attrition | B35: Yes
A37: Business Unit | B37: %
A38: Commercial | B38: 0.22147651
A39: Corporate | B39: 0.15436242
A40: Insurance | B40: 0.20805369
A41: Operations | B41: 0.16107383
A42: People | B42: 0.087248322
A43: Technology | B43: 0.16778523
A44: Grand Total | B44: 1
A49: Attrition | B49: Yes
A51: Country | B51: %
A52: UK | B52: 0.40268456
A53: US | B53: 0.24832215
A54: Canada | B54: 0.1409396
A55: Singapore | B55: 0.087248322
A56: Ireland | B56: 0.067114094
A57: Germany | B57: 0.053691275
A58: Grand Total | B58: 1
A62: Attrition | B62: Yes
A64: Job Level | B64: No of Employees
A65: Professional | B65: 0.3557047
A66: Senior | B66: 0.24161074
A67: Entry | B67: 0.17449664
A68: Manager | B68: 0.15436242
A69: Senior Manager | B69: 0.073825503
A70: Grand Total | B70: 1
D72: Attrition | E72: Yes | G72: Attrition | H72: Yes
A74: Attrition | B74: Yes | D74: Promotion | E74: No of Employees | G74: Working Arrangement | H74: No of Employees
D75: No | E75: 0.85234899 | G75: Hybrid | H75: 0.61073826
A76: Age group | B76: No of Employees | D76: Yes | E76: 0.14765101 | G76: Office | H76: 0.20134228
A77: 32-45 | B77: 0.59731544 | D77: Grand Total | E77: 1 | G77: Remote | H77: 0.18791946
A78: 18-31 | B78: 0.22818792 | G78: Grand Total | H78: 1
A79: 46-59 | B79: 0.16778523
A80: 60-73 | B80: 0.0067114094
A81: Grand Total | B81: 1
A85: Attrition | B85: Yes | D85: Attrition | E85: Yes
A87: Tenure Band | B87: No of Employees | D87: Performance Ratings | E87: No of Employees
A88: 2-<5 years | B88: 0.44295302 | D88: Meets Expectations | E88: 0.57718121
A89: 5-<10 years | B89: 0.32885906 | D89: Exceeds Expectations | E89: 0.27516779
A90: 1-<2 years | B90: 0.12080537 | D90: Needs Improvement | E90: 0.080536913
A91: Less than 1 year | B91: 0.067114094 | D91: Outstanding | E91: 0.067114094
A92: 10-<15 years | B92: 0.040268456 | D92: Grand Total | E92: 1
A93: Grand Total | B93: 1
A96: ATTRITION ANALYTICS
A98: Department | B98: Attrition Rate
A99: Finance | B99: 0.1796875
A100: HR | B100: 0.1625
A101: Claims | B101: 0.16129032
A102: IT | B102: 0.15923567
A103: Sales | B103: 0.15
A104: Operations | B104: 0.14723926
A105: Marketing | B105: 0.11688312
A106: Underwriting | B106: 0.099099099
A107: Grand Total | B107: 0.149
A110: Gender | B110: Attrition Rate
A111: Female | B111: 0.17261905
A112: Male | B112: 0.125
A113: Grand Total | B113: 0.149
A117: Age group | B117: Attrition Rate
A118: 60-73 | B118: 0.5
A119: 32-45 | B119: 0.16240876
A120: 18-31 | B120: 0.13877551
A121: 46-59 | B121: 0.12195122
A122: Grand Total | B122: 0.149
A126: Tenure Band | B126: Attrition Rate
A127: Less than 1 year | B127: 0.18867925
A128: 2-<5 years | B128: 0.15789474
A129: 5-<10 years | B129: 0.15076923
A130: 1-<2 years | B130: 0.13235294
A131: 10-<15 years | B131: 0.096774194
A132: 16+ years | B132: 0
A133: Grand Total | B133: 0.149
A137: Job level | B137: Attrition Rate
...

Sheet Predictive Model
A1: Employee ID | B1: Gender | C1: Department | D1: Business Unit | E1: Country | F1: Job Level | G1: Age | H1: Tenure (Years) | I1: Time in Role (Years) | J1: Compa-Ratio | K1: Performance Rating | L1: Promotion in Last 2 Years | M1: Months Since Salary Increase | N1: Engagement Score | O1: Absence Days | P1: Manager Tenure (Years) | Q1: Working Arrangement | R1: Overtime | S1: Training Hours | T1: Leaver flag | U1: Gender_Female | V1: Perf_Needs_Improvement | W1: Perf_Exceeds | X1: Perf_Outstanding | Y1: Job_Entry | Z1: Job_Manager | AA1: Job_Senior | AB1: Job_Senior_Manager | AC1: Dept_Claims | AD1: Dept_Finance | AE1: Dept_HR | AF1: Dept_IT | AG1: Dept_Marketing | AH1: Dept_Sales | AI1: Dept_Underwriting | AJ1: Country_Canada | AK1: Country_Germany | AL1: Country_Ireland | AM1: Country_Singapore | AN1: Country_US | AO1: Work_Office | AP1: Work_Remote | AQ1: Column1
A2: E0001 | B2: =VLOOKUP(EmployeeData3[[#This Row],[Employee ID]],GenderData[#All],2,FALSE) -> Female | C2: Sales | D2: Commercial | E2: UK | F2: Professional | G2: 39 | H2: 1.9 | I2: 1.9 | J2: 1.12 | K2: Meets Expectations | L2: No | M2: 19 | N2: 86 | O2: 2 | P2: 5.2 | Q2: Remote | R2: No | S2: 44 | T2: 0 | U2: =IF(EmployeeData3[[#This Row],[Gender]]="Female",1,0) -> 1 | V2: =IF(EmployeeData3[[#This Row],[Performance Rating]]="Needs Improvement",1,0) -> 0 | W2: =IF(EmployeeData3[[#This Row],[Performance Rating]]="Exceeds Expectations",1,0) -> 0 | X2: =IF(EmployeeData3[[#This Row],[Performance Rating]]="Outstanding",1,0) -> 0 | Y2: =IF(EmployeeData3[[#This Row],[Job Level]]="Entry",1,0) -> 0 | Z2: =IF(EmployeeData3[[#This Row],[Job Level]]="Manager",1,0) -> 0 | AA2: =IF(EmployeeData3[[#This Row],[Job Level]]="Senior",1,0) -> 0 | AB2: =IF(EmployeeData3[[#This Row],[Job Level]]="Senior Manager",1,0) -> 0 | AC2: =IF(EmployeeData3[[#This Row],[Department]]="Claims",1,0) -> 0 | AD2: =IF(EmployeeData3[[#This Row],[Department]]="Finance",1,0) -> 0 | AE2: =IF(EmployeeData3[[#This Row],[Department]]="HR",1,0) -> 0 | AF2: =IF(EmployeeData3[[#This Row],[Department]]="IT",1,0) -> 0 | AG2: =IF(EmployeeData3[[#This Row],[Department]]="Marketing",1,0) -> 0 | AH2: =IF(EmployeeData3[[#This Row],[Department]]="Sales",1,0) -> 1 | AI2: =IF(EmployeeData3[[#This Row],[Department]]="Underwriting",1,0) -> 0 | AJ2: =IF(EmployeeData3[[#This Row],[Country]]="Canada",1,0) -> 0 | AK2: =IF(EmployeeData3[[#This Row],[Country]]="Germany",1,0) -> 0 | AL2: =IF(EmployeeData3[[#This Row],[Country]]="Ireland",1,0) -> 0 | AM2: =IF(EmployeeData3[[#This Row],[Country]]="Singapore",1,0) -> 0 | AN2: =IF(EmployeeData3[[#This Row],[Country]]="US",1,0) -> 0 | AO2: =IF(EmployeeData3[[#This Row],[Working Arrangement]]="Office",1,0) -> 0 | AP2: =IF(EmployeeData3[[#This Row],[Working Arrangement]]="Remote",1,0) -> 1 | AQ2: ='Logistics Regression'!#REF! + SUMPRODUCT(B2:J2, 'Logistics Regression'!#REF!) -> #REF!
A3: E0002 | B3: =VLOOKUP(EmployeeData3[[#This Row],[Employee ID]],GenderData[#All],2,FALSE) -> Male | C3: Claims | D3: Insurance | E3: Germany | F3: Senior | G3: 32 | H3: 2 | I3: 2 | J3: 0.95 | K3: Meets Expectations | L3: No | M3: 8 | N3: 91 | O3: 2 | P3: 2.8 | Q3: Hybrid | R3: No | S3: 0 | T3: 0 | U3: =IF(EmployeeData3[[#This Row],[Gender]]="Female",1,0) -> 0 | V3: =IF(EmployeeData3[[#This Row],[Performance Rating]]="Needs Improvement",1,0) -> 0 | W3: =IF(EmployeeData3[[#This Row],[Performance Rating]]="Exceeds Expectations",1,0) -> 0 | X3: =IF(EmployeeData3[[#This Row],[Performance Rating]]="Outstanding",1,0) -> 0 | Y3: =IF(EmployeeData3[[#This Row],[Job Level]]="Entry",1,0) -> 0 | Z3: =IF(EmployeeData3[[#This Row],[Job Level]]="Manager",1,0) -> 0 | AA3: =IF(EmployeeData3[[#This Row],[Job Level]]="Senior",1,0) -> 1 | AB3: =IF(EmployeeData3[[#This Row],[Job Level]]="Senior Manager",1,0) -> 0 | AC3: =IF(EmployeeData3[[#This Row],[Department]]="Claims",1,0) -> 1 | AD3: =IF(EmployeeData3[[#This Row],[Department]]="Finance",1,0) -> 0 | AE3: =IF(EmployeeData3[[#This Row],[Department]]="HR",1,0) -> 0 | AF3: =IF(EmployeeData3[[#This Row],[Department]]="IT",1,0) -> 0 | AG3: =IF(EmployeeData3[[#This Row],[Department]]="Marketing",1,0) -> 0 | AH3: =IF(EmployeeData3[[#This Row],[Department]]="Sales",1,0) -> 0 | AI3: =IF(EmployeeData3[[#This Row],[Department]]="Underwriting",1,0) -> 0 | AJ3: =IF(EmployeeData3[[#This Row],[Country]]="Canada",1,0) -> 0 | AK3: =IF(EmployeeData3[[#This Row],[Country]]="Germany",1,0) -> 1 | AL3: =IF(EmployeeData3[[#This Row],[Country]]="Ireland",1,0) -> 0 | AM3: =IF(EmployeeData3[[#This Row],[Country]]="Singapore",1,0) -> 0 | AN3: =IF(EmployeeData3[[#This Row],[Country]]="US",1,0) -> 0 | AO3: =IF(EmployeeData3[[#This Row],[Working Arrangement]]="Office",1,0) -> 0 | AP3: =IF(EmployeeData3[[#This Row],[Working Arrangement]]="Remote",1,0) -> 0 | AQ3: ='Logistics Regression'!#REF! + SUMPRODUCT(B3:J3, 'Logistics Regression'!#REF!) -> #REF!
A4: E0003 | B4: =VLOOKUP(EmployeeData3[[#This Row],[Employee ID]],GenderData[#All],2,FALSE) -> Male | C4: Marketing | D4: Commercial | E4: UK | F4: Manager | G4: 21 | H4: 7.2 | I4: 1.2 | J4: 0.89 | K4: Exceeds Expectations | L4: No | M4: 31 | N4: 55 | O4: 3 | P4: 0.5 | Q4: Remote | R4: Yes | S4: 37 | T4: 0 | U4: =IF(EmployeeData3[[#This Row],[Gender]]="Female",1,0) -> 0 | V4: =IF(EmployeeData3[[#This Row],[Performance Rating]]="Needs Improvement",1,0) -> 0 | W4: =IF(EmployeeData3[[#This Row],[Performance Rating]]="Exceeds Expectations",1,0) -> 1 | X4: =IF(EmployeeData3[[#This Row],[Performance Rating]]="Outstanding",1,0) -> 0 | Y4: =IF(EmployeeData3[[#This Row],[Job Level]]="Entry",1,0) -> 0 | Z4: =IF(EmployeeData3[[#This Row],[Job Level]]="Manager",1,0) -> 1 | AA4: =IF(EmployeeData3[[#This Row],[Job Level]]="Senior",1,0) -> 0 | AB4: =IF(EmployeeData3[[#This Row],[Job Level]]="Senior Manager",1,0) -> 0 | AC4: =IF(EmployeeData3[[#This Row],[Department]]="Claims",1,0) -> 0 | AD4: =IF(EmployeeData3[[#This Row],[Department]]="Finance",1,0) -> 0 | AE4: =IF(EmployeeData3[[#This Row],[Department]]="HR",1,0) -> 0 | AF4: =IF(EmployeeData3[[#This Row],[Department]]="IT",1,0) -> 0 | AG4: =IF(EmployeeData3[[#This Row],[Department]]="Marketing",1,0) -> 1 | AH4: =IF(EmployeeData3[[#This Row],[Department]]="Sales",1,0) -> 0 | AI4: =IF(EmployeeData3[[#This Row],[Department]]="Underwriting",1,0) -> 0 | AJ4: =IF(EmployeeData3[[#This Row],[Country]]="Canada",1,0) -> 0 | AK4: =IF(EmployeeData3[[#This Row],[Country]]="Germany",1,0) -> 0 | AL4: =IF(EmployeeData3[[#This Row],[Country]]="Ireland",1,0) -> 0 | AM4: =IF(EmployeeData3[[#This Row],[Country]]="Singapore",1,0) -> 0 | AN4: =IF(EmployeeData3[[#This Row],[Country]]="US",1,0) -> 0 | AO4: =IF(EmployeeData3[[#This Row],[Working Arrangement]]="Office",1,0) -> 0 | AP4: =IF(EmployeeData3[[#This Row],[Working Arrangement]]="Remote",1,0) -> 1 | AQ4: ='Logistics Regression'!#REF! + SUMPRODUCT(B4:J4, 'Logistics Regression'!#REF!) -> #REF!
A5: E0004 | B5: =VLOOKUP(EmployeeData3[[#This Row],[Employee ID]],GenderData[#All],2,FALSE) -> Female | C5: Operations | D5: Operations | E5: Singapore | F5: Senior | G5: 48 | H5: 2 | I5: 2 | J5: 0.99 | K5: Exceeds Expectations | L5: No | M5: 35 | N5: 78 | O5: 3 | P5: 2.3 | Q5: Remote | R5: No | S5: 27 | T5: 0 | U5: =IF(EmployeeData3[[#This Row],[Gender]]="Female",1,0) -> 1 | V5: =IF(EmployeeData3[[#This Row],[Performance Rating]]="Needs Improvement",1,0) -> 0 | W5: =IF(EmployeeData3[[#This Row],[Performance Rating]]="Exceeds Expectations",1,0) -> 1 | X5: =IF(EmployeeData3[[#This Row],[Performance Rating]]="Outstanding",1,0) -> 0 | Y5: =IF(EmployeeData3[[#This Row],[Job Level]]="Entry",1,0) -> 0 | Z5: =IF(EmployeeData3[[#This Row],[Job Level]]="Manager",1,0) -> 0 | AA5: =IF(EmployeeData3[[#This Row],[Job Level]]="Senior",1,0) -> 1 | AB5: =IF(EmployeeData3[[#This Row],[Job Level]]="Senior Manager",1,0) -> 0 | AC5: =IF(EmployeeData3[[#This Row],[Department]]="Claims",1,0) -> 0 | AD5: =IF(EmployeeData3[[#This Row],[Department]]="Finance",1,0) -> 0 | AE5: =IF(EmployeeData3[[#This Row],[Department]]="HR",1,0) -> 0 | AF5: =IF(EmployeeData3[[#This Row],[Department]]="IT",1,0) -> 0 | AG5: =IF(EmployeeData3[[#This Row],[Department]]="Marketing",1,0) -> 0 | AH5: =IF(EmployeeData3[[#This Row],[Department]]="Sales",1,0) -> 0 | AI5: =IF(EmployeeData3[[#This Row],[Department]]="Underwriting",1,0) -> 0 | AJ5: =IF(EmployeeData3[[#This Row],[Country]]="Canada",1,0) -> 0 | AK5: =IF(EmployeeData3[[#This Row],[Country]]="Germany",1,0) -> 0 | AL5: =IF(EmployeeData3[[#This Row],[Country]]="Ireland",1,0) -> 0 | AM5: =IF(EmployeeData3[[#This Row],[Country]]="Singapore",1,0) -> 1 | AN5: =IF(EmployeeData3[[#This Row],[Country]]="US",1,0) -> 0 | AO5: =IF(EmployeeData3[[#This Row],[Working Arrangement]]="Office",1,0) -> 0 | AP5: =IF(EmployeeData3[[#This Row],[Working Arrangement]]="Remote",1,0) -> 1 | AQ5: ='Logistics Regression'!#REF! + SUMPRODUCT(B5:J5, 'Logistics Regression'!#REF!) -> #REF!
A6: E0005 | B6: =VLOOKUP(EmployeeData3[[#This Row],[Employee ID]],GenderData[#All],2,FALSE) -> Male | C6: Finance | D6: Corporate | E6: US | F6: Manager | G6: 23 | H6: 3.9 | I6: 2.3 | J6: 1.04 | K6: Meets Expectations | L6: No | M6: 16 | N6: 81 | O6: 5 | P6: 4.3 | Q6: Hybrid | R6: Yes | S6: 35 | T6: 0 | U6: =IF(EmployeeData3[[#This Row],[Gender]]="Female",1,0) -> 0 | V6: =IF(EmployeeData3[[#This Row],[Performance Rating]]="Needs Improvement",1,0) -> 0 | W6: =IF(EmployeeData3[[#This Row],[Performance Rating]]="Exceeds Expectations",1,0) -> 0 | X6: =IF(EmployeeData3[[#This Row],[Performance Rating]]="Outstanding",1,0) -> 0 | Y6: =IF(EmployeeData3[[#This Row],[Job Level]]="Entry",1,0) -> 0 | Z6: =IF(EmployeeData3[[#This Row],[Job Level]]="Manager",1,0) -> 1 | AA6: =IF(EmployeeData3[[#This Row],[Job Level]]="Senior",1,0) -> 0 | AB6: =IF(EmployeeData3[[#This Row],[Job Level]]="Senior Manager",1,0) -> 0 | AC6: =IF(EmployeeData3[[#This Row],[Department]]="Claims",1,0) -> 0 | AD6: =IF(EmployeeData3[[#This Row],[Department]]="Finance",1,0) -> 1 | AE6: =IF(EmployeeData3[[#This Row],[Department]]="HR",1,0) -> 0 | AF6: =IF(EmployeeData3[[#This Row],[Department]]="IT",1,0) -> 0 | AG6: =IF(EmployeeData3[[#This Row],[Department]]="Marketing",1,0) -> 0 | AH6: =IF(EmployeeData3[[#This Row],[Department]]="Sales",1,0) -> 0 | AI6: =IF(EmployeeData3[[#This Row],[Department]]="Underwriting",1,0) -> 0 | AJ6: =IF(EmployeeData3[[#This Row],[Country]]="Canada",1,0) -> 0 | AK6: =IF(EmployeeData3[[#This Row],[Country]]="Germany",1,0) -> 0 | AL6: =IF(EmployeeData3[[#This Row],[Country]]="Ireland",1,0) -> 0 | AM6: =IF(EmployeeData3[[#This Row],[Country]]="Singapore",1,0) -> 0 | AN6: =IF(EmployeeData3[[#This Row],[Country]]="US",1,0) -> 1 | AO6: =IF(EmployeeData3[[#This Row],[Working Arrangement]]="Office",1,0) -> 0 | AP6: =IF(EmployeeData3[[#This Row],[Working Arrangement]]="Remote",1,0) -> 0 | AQ6: ='Logistics Regression'!#REF! + SUMPRODUCT(B6:J6, 'Logistics Regression'!#REF!) -> #REF!
A7: E0006 | B7: =VLOOKUP(EmployeeData3[[#This Row],[Employee ID]],GenderData[#All],2,FALSE) -> Female | C7: Finance | D7: Corporate | E7: Germany | F7: Senior | G7: 43 | H7: 2.1 | I7: 1.9 | J7: 0.88 | K7: Meets Expectations | L7: No | M7: 11 | N7: 80 | O7: 9 | P7: 3.4 | Q7: Hybrid | R7: No | S7: 17 | T7: 0 | U7: =IF(EmployeeData3[[#This Row],[Gender]]="Female",1,0) -> 1 | V7: =IF(EmployeeData3[[#This Row],[Performance Rating]]="Needs Improvement",1,0) -> 0 | W7: =IF(EmployeeData3[[#This Row],[Performance Rating]]="Exceeds Expectations",1,0) -> 0 | X7: =IF(EmployeeData3[[#This Row],[Performance Rating]]="Outstanding",1,0) -> 0 | Y7: =IF(EmployeeData3[[#This Row],[Job Level]]="Entry",1,0) -> 0 | Z7: =IF(EmployeeData3[[#This Row],[Job Level]]="Manager",1,0) -> 0 | AA7: =IF(EmployeeData3[[#This Row],[Job Level]]="Senior",1,0) -> 1 | AB7: =IF(EmployeeData3[[#This Row],[Job Level]]="Senior Manager",1,0) -> 0 | AC7: =IF(EmployeeData3[[#This Row],[Department]]="Claims",1,0) -> 0 | AD7: =IF(EmployeeData3[[#This Row],[Department]]="Finance",1,0) -> 1 | AE7: =IF(EmployeeData3[[#This Row],[Department]]="HR",1,0) -> 0 | AF7: =IF(EmployeeData3[[#This Row],[Department]]="IT",1,0) -> 0 | AG7: =IF(EmployeeData3[[#This Row],[Department]]="Marketing",1,0) -> 0 | AH7: =IF(EmployeeData3[[#This Row],[Department]]="Sales",1,0) -> 0 | AI7: =IF(EmployeeData3[[#This Row],[Department]]="Underwriting",1,0) -> 0 | AJ7: =IF(EmployeeData3[[#This Row],[Country]]="Canada",1,0) -> 0 | AK7: =IF(EmployeeData3[[#This Row],[Country]]="Germany",1,0) -> 1 | AL7: =IF(EmployeeData3[[#This Row],[Country]]="Ireland",1,0) -> 0 | AM7: =IF(EmployeeData3[[#This Row],[Country]]="Singapore",1,0) -> 0 | AN7: =IF(EmployeeData3[[#This Row],[Country]]="US",1,0) -> 0 | AO7: =IF(EmployeeData3[[#This Row],[Working Arrangement]]="Office",1,0) -> 0 | AP7: =IF(EmployeeData3[[#This Row],[Working Arrangement]]="Remote",1,0) -> 0 | AQ7: ='Logistics Regression'!#REF! + SUMPRODUCT(B7:J7, 'Logistics Regression'!#REF!) -> #REF!
A8: E0007 | B8: =VLOOKUP(EmployeeData3[[#This Row],[Employee ID]],GenderData[#All],2,FALSE) -> Female | C8: IT | D8: Technology | E8: UK | F8: Senior | G8: 38 | H8: 0.3 | I8: 0.3 | J8: 0.97 | K8: Meets Expectations | L8: No | M8: 14 | N8: 78 | O8: 2 | P8: 3.7 | Q8: Office | R8: Yes | S8: 3 | T8: 0 | U8: =IF(EmployeeData3[[#This Row],[Gender]]="Female",1,0) -> 1 | V8: =IF(EmployeeData3[[#This Row],[Performance Rating]]="Needs Improvement",1,0) -> 0 | W8: =IF(EmployeeData3[[#This Row],[Performance Rating]]="Exceeds Expectations",1,0) -> 0 | X8: =IF(EmployeeData3[[#This Row],[Performance Rating]]="Outstanding",1,0) -> 0 | Y8: =IF(EmployeeData3[[#This Row],[Job Level]]="Entry",1,0) -> 0 | Z8: =IF(EmployeeData3[[#This Row],[Job Level]]="Manager",1,0) -> 0 | AA8: =IF(EmployeeData3[[#This Row],[Job Level]]="Senior",1,0) -> 1 | AB8: =IF(EmployeeData3[[#This Row],[Job Level]]="Senior Manager",1,0) -> 0 | AC8: =IF(EmployeeData3[[#This Row],[Department]]="Claims",1,0) -> 0 | AD8: =IF(EmployeeData3[[#This Row],[Department]]="Finance",1,0) -> 0 | AE8: =IF(EmployeeData3[[#This Row],[Department]]="HR",1,0) -> 0 | AF8: =IF(EmployeeData3[[#This Row],[Department]]="IT",1,0) -> 1 | AG8: =IF(EmployeeData3[[#This Row],[Department]]="Marketing",1,0) -> 0 | AH8: =IF(EmployeeData3[[#This Row],[Department]]="Sales",1,0) -> 0 | AI8: =IF(EmployeeData3[[#This Row],[Department]]="Underwriting",1,0) -> 0 | AJ8: =IF(EmployeeData3[[#This Row],[Country]]="Canada",1,0) -> 0 | AK8: =IF(EmployeeData3[[#This Row],[Country]]="Germany",1,0) -> 0 | AL8: =IF(EmployeeData3[[#This Row],[Country]]="Ireland",1,0) -> 0 | AM8: =IF(EmployeeData3[[#This Row],[Country]]="Singapore",1,0) -> 0 | AN8: =IF(EmployeeData3[[#This Row],[Country]]="US",1,0) -> 0 | AO8: =IF(EmployeeData3[[#This Row],[Working Arrangement]]="Office",1,0) -> 1 | AP8: =IF(EmployeeData3[[#This Row],[Working Arrangement]]="Remote",1,0) -> 0 | AQ8: ='Logistics Regression'!#REF! + SUMPRODUCT(B8:J8, 'Logistics Regression'!#REF!) -> #REF!
A9: E0008 | B9: =VLOOKUP(EmployeeData3[[#This Row],[Employee ID]],GenderData[#All],2,FALSE) -> Male | C9: Underwriting | D9: Insurance | E9: UK | F9: Manager | G9: 57 | H9: 7 | I9: 3.1 | J9: 1 | K9: Needs Improvement | L9: Yes | M9: 22 | N9: 51 | O9: 9 | P9: 4.6 | Q9: Hybrid | R9: No | S9: 31 | T9: 0 | U9: =IF(EmployeeData3[[#This Row],[Gender]]="Female",1,0) -> 0 | V9: =IF(EmployeeData3[[#This Row],[Performance Rating]]="Needs Improvement",1,0) -> 1 | W9: =IF(EmployeeData3[[#This Row],[Performance Rating]]="Exceeds Expectations",1,0) -> 0 | X9: =IF(EmployeeData3[[#This Row],[Performance Rating]]="Outstanding",1,0) -> 0 | Y9: =IF(EmployeeData3[[#This Row],[Job Level]]="Entry",1,0) -> 0 | Z9: =IF(EmployeeData3[[#This Row],[Job Level]]="Manager",1,0) -> 1 | AA9: =IF(EmployeeData3[[#This Row],[Job Level]]="Senior",1,0) -> 0 | AB9: =IF(EmployeeData3[[#This Row],[Job Level]]="Senior Manager",1,0) -> 0 | AC9: =IF(EmployeeData3[[#This Row],[Department]]="Claims",1,0) -> 0 | AD9: =IF(EmployeeData3[[#This Row],[Department]]="Finance",1,0) -> 0 | AE9: =IF(EmployeeData3[[#This Row],[Department]]="HR",1,0) -> 0 | AF9: =IF(EmployeeData3[[#This Row],[Department]]="IT",1,0) -> 0 | AG9: =IF(EmployeeData3[[#This Row],[Department]]="Marketing",1,0) -> 0 | AH9: =IF(EmployeeData3[[#This Row],[Department]]="Sales",1,0) -> 0 | AI9: =IF(EmployeeData3[[#This Row],[Department]]="Underwriting",1,0) -> 1 | AJ9: =IF(EmployeeData3[[#This Row],[Country]]="Canada",1,0) -> 0 | AK9: =IF(EmployeeData3[[#This Row],[Country]]="Germany",1,0) -> 0 | AL9: =IF(EmployeeData3[[#This Row],[Country]]="Ireland",1,0) -> 0 | AM9: =IF(EmployeeData3[[#This Row],[Country]]="Singapore",1,0) -> 0 | AN9: =IF(EmployeeData3[[#This Row],[Country]]="US",1,0) -> 0 | AO9: =IF(EmployeeData3[[#This Row],[Working Arrangement]]="Office",1,0) -> 0 | AP9: =IF(EmployeeData3[[#This Row],[Working Arrangement]]="Remote",1,0) -> 0 | AQ9: ='Logistics Regression'!#REF! + SUMPRODUCT(B9:J9, 'Logistics Regression'!#REF!) -> #REF!
A10: E0009 | B10: =VLOOKUP(EmployeeData3[[#This Row],[Employee ID]],GenderData[#All],2,FALSE) -> Male | C10: Operations | D10: Operations | E10: Canada | F10: Professional | G10: 47 | H10: 4.1 | I10: 4.1 | J10: 1.01 | K10: Exceeds Expectations | L10: No | M10: 28 | N10: 63 | O10: 8 | P10: 1.1 | Q10: Hybrid | R10: Yes | S10: 13 | T10: 0 | U10: =IF(EmployeeData3[[#This Row],[Gender]]="Female",1,0) -> 0 | V10: =IF(EmployeeData3[[#This Row],[Performance Rating]]="Needs Improvement",1,0) -> 0 | W10: =IF(EmployeeData3[[#This Row],[Performance Rating]]="Exceeds Expectations",1,0) -> 1 | X10: =IF(EmployeeData3[[#This Row],[Performance Rating]]="Outstanding",1,0) -> 0 | Y10: =IF(EmployeeData3[[#This Row],[Job Level]]="Entry",1,0) -> 0 | Z10: =IF(EmployeeData3[[#This Row],[Job Level]]="Manager",1,0) -> 0 | AA10: =IF(EmployeeData3[[#This Row],[Job Level]]="Senior",1,0) -> 0 | AB10: =IF(EmployeeData3[[#This Row],[Job Level]]="Senior Manager",1,0) -> 0 | AC10: =IF(EmployeeData3[[#This Row],[Department]]="Claims",1,0) -> 0 | AD10: =IF(EmployeeData3[[#This Row],[Department]]="Finance",1,0) -> 0 | AE10: =IF(EmployeeData3[[#This Row],[Department]]="HR",1,0) -> 0 | AF10: =IF(EmployeeData3[[#This Row],[Department]]="IT",1,0) -> 0 | AG10: =IF(EmployeeData3[[#This Row],[Department]]="Marketing",1,0) -> 0 | AH10: =IF(EmployeeData3[[#This Row],[Department]]="Sales",1,0) -> 0 | AI10: =IF(EmployeeData3[[#This Row],[Department]]="Underwriting",1,0) -> 0 | AJ10: =IF(EmployeeData3[[#This Row],[Country]]="Canada",1,0) -> 1 | AK10: =IF(EmployeeData3[[#This Row],[Country]]="Germany",1,0) -> 0 | AL10: =IF(EmployeeData3[[#This Row],[Country]]="Ireland",1,0) -> 0 | AM10: =IF(EmployeeData3[[#This Row],[Country]]="Singapore",1,0) -> 0 | AN10: =IF(EmployeeData3[[#This Row],[Country]]="US",1,0) -> 0 | AO10: =IF(EmployeeData3[[#This Row],[Working Arrangement]]="Office",1,0) -> 0 | AP10: =IF(EmployeeData3[[#This Row],[Working Arrangement]]="Remote",1,0) -> 0 | AQ10: ='Logistics Regression'!#REF! + SUMPRODUCT(B10:J10, 'Logistics Regression'!#REF!) -> #REF!
A11: E0010 | B11: =VLOOKUP(EmployeeData3[[#This Row],[Employee ID]],GenderData[#All],2,FALSE) -> Male | C11: Marketing | D11: Commercial | E11: US | F11: Professional | G11: 33 | H11: 5.6 | I11: 5.6 | J11: 1.01 | K11: Meets Expectations | L11: No | M11: 21 | N11: 55 | O11: 8 | P11: 4.7 | Q11: Hybrid | R11: No | S11: 7 | T11: 1 | U11: =IF(EmployeeData3[[#This Row],[Gender]]="Female",1,0) -> 0 | V11: =IF(EmployeeData3[[#This Row],[Performance Rating]]="Needs Improvement",1,0) -> 0 | W11: =IF(EmployeeData3[[#This Row],[Performance Rating]]="Exceeds Expectations",1,0) -> 0 | X11: =IF(EmployeeData3[[#This Row],[Performance Rating]]="Outstanding",1,0) -> 0 | Y11: =IF(EmployeeData3[[#This Row],[Job Level]]="Entry",1,0) -> 0 | Z11: =IF(EmployeeData3[[#This Row],[Job Level]]="Manager",1,0) -> 0 | AA11: =IF(EmployeeData3[[#This Row],[Job Level]]="Senior",1,0) -> 0 | AB11: =IF(EmployeeData3[[#This Row],[Job Level]]="Senior Manager",1,0) -> 0 | AC11: =IF(EmployeeData3[[#This Row],[Department]]="Claims",1,0) -> 0 | AD11: =IF(EmployeeData3[[#This Row],[Department]]="Finance",1,0) -> 0 | AE11: =IF(EmployeeData3[[#This Row],[Department]]="HR",1,0) -> 0 | AF11: =IF(EmployeeData3[[#This Row],[Department]]="IT",1,0) -> 0 | AG11: =IF(EmployeeData3[[#This Row],[Department]]="Marketing",1,0) -> 1 | AH11: =IF(EmployeeData3[[#This Row],[Department]]="Sales",1,0) -> 0 | AI11: =IF(EmployeeData3[[#This Row],[Department]]="Underwriting",1,0) -> 0 | AJ11: =IF(EmployeeData3[[#This Row],[Country]]="Canada",1,0) -> 0 | AK11: =IF(EmployeeData3[[#This Row],[Country]]="Germany",1,0) -> 0 | AL11: =IF(EmployeeData3[[#This Row],[Country]]="Ireland",1,0) -> 0 | AM11: =IF(EmployeeData3[[#This Row],[Country]]="Singapore",1,0) -> 0 | AN11: =IF(EmployeeData3[[#This Row],[Country]]="US",1,0) -> 1 | AO11: =IF(EmployeeData3[[#This Row],[Working Arrangement]]="Office",1,0) -> 0 | AP11: =IF(EmployeeData3[[#This Row],[Working Arrangement]]="Remote",1,0) -> 0 | AQ11: ='Logistics Regression'!#REF! + SUMPRODUCT(B11:J11, 'Logistics Regression'!#REF!) -> #REF!
A12: E0011 | B12: =VLOOKUP(EmployeeData3[[#This Row],[Employee ID]],GenderData[#All],2,FALSE) -> Female | C12: IT | D12: Technology | E12: UK | F12: Professional | G12: 32 | H12: 0.9 | I12: 0.9 | J12: 1.03 | K12: Exceeds Expectations | L12: No | M12: 17 | N12: 70 | O12: 5 | P12: 8.4 | Q12: Hybrid | R12: No | S12: 8 | T12: 1 | U12: =IF(EmployeeData3[[#This Row],[Gender]]="Female",1,0) -> 1 | V12: =IF(EmployeeData3[[#This Row],[Performance Rating]]="Needs Improvement",1,0) -> 0 | W12: =IF(EmployeeData3[[#This Row],[Performance Rating]]="Exceeds Expectations",1,0) -> 1 | X12: =IF(EmployeeData3[[#This Row],[Performance Rating]]="Outstanding",1,0) -> 0 | Y12: =IF(EmployeeData3[[#This Row],[Job Level]]="Entry",1,0) -> 0 | Z12: =IF(EmployeeData3[[#This Row],[Job Level]]="Manager",1,0) -> 0 | AA12: =IF(EmployeeData3[[#This Row],[Job Level]]="Senior",1,0) -> 0 | AB12: =IF(EmployeeData3[[#This Row],[Job Level]]="Senior Manager",1,0) -> 0 | AC12: =IF(EmployeeData3[[#This Row],[Department]]="Claims",1,0) -> 0 | AD12: =IF(EmployeeData3[[#This Row],[Department]]="Finance",1,0) -> 0 | AE12: =IF(EmployeeData3[[#This Row],[Department]]="HR",1,0) -> 0 | AF12: =IF(EmployeeData3[[#This Row],[Department]]="IT",1,0) -> 1 | AG12: =IF(EmployeeData3[[#This Row],[Department]]="Marketing",1,0) -> 0 | AH12: =IF(EmployeeData3[[#This Row],[Department]]="Sales",1,0) -> 0 | AI12: =IF(EmployeeData3[[#This Row],[Department]]="Underwriting",1,0) -> 0 | AJ12: =IF(EmployeeData3[[#This Row],[Country]]="Canada",1,0) -> 0 | AK12: =IF(EmployeeData3[[#This Row],[Country]]="Germany",1,0) -> 0 | AL12: =IF(EmployeeData3[[#This Row],[Country]]="Ireland",1,0) -> 0 | AM12: =IF(EmployeeData3[[#This Row],[Country]]="Singapore",1,0) -> 0 | AN12: =IF(EmployeeData3[[#This Row],[Country]]="US",1,0) -> 0 | AO12: =IF(EmployeeData3[[#This Row],[Working Arrangement]]="Office",1,0) -> 0 | AP12: =IF(EmployeeData3[[#This Row],[Working Arrangement]]="Remote",1,0) -> 0 | AQ12: ='Logistics Regression'!#REF! + SUMPRODUCT(B12:J12, 'Logistics Regression'!#REF!) -> #REF!
A13: E0012 | B13: =VLOOKUP(EmployeeData3[[#This Row],[Employee ID]],GenderData[#All],2,FALSE) -> Female | C13: Claims | D13: Insurance | E13: UK | F13: Senior Manager | G13: 52 | H13: 2.6 | I13: 2.4 | J13: 0.91 | K13: Exceeds Expectations | L13: No | M13: 29 | N13: 80 | O13: 2 | P13: 2.1 | Q13: Hybrid | R13: No | S13: 31 | T13: 0 | U13: =IF(EmployeeData3[[#This Row],[Gender]]="Female",1,0) -> 1 | V13: =IF(EmployeeData3[[#This Row],[Performance Rating]]="Needs Improvement",1,0) -> 0 | W13: =IF(EmployeeData3[[#This Row],[Performance Rating]]="Exceeds Expectations",1,0) -> 1 | X13: =IF(EmployeeData3[[#This Row],[Performance Rating]]="Outstanding",1,0) -> 0 | Y13: =IF(EmployeeData3[[#This Row],[Job Level]]="Entry",1,0) -> 0 | Z13: =IF(EmployeeData3[[#This Row],[Job Level]]="Manager",1,0) -> 0 | AA13: =IF(EmployeeData3[[#This Row],[Job Level]]="Senior",1,0) -> 0 | AB13: =IF(EmployeeData3[[#This Row],[Job Level]]="Senior Manager",1,0) -> 1 | AC13: =IF(EmployeeData3[[#This Row],[Department]]="Claims",1,0) -> 1 | AD13: =IF(EmployeeData3[[#This Row],[Department]]="Finance",1,0) -> 0 | AE13: =IF(EmployeeData3[[#This Row],[Department]]="HR",1,0) -> 0 | AF13: =IF(EmployeeData3[[#This Row],[Department]]="IT",1,0) -> 0 | AG13: =IF(EmployeeData3[[#This Row],[Department]]="Marketing",1,0) -> 0 | AH13: =IF(EmployeeData3[[#This Row],[Department]]="Sales",1,0) -> 0 | AI13: =IF(EmployeeData3[[#This Row],[Department]]="Underwriting",1,0) -> 0 | AJ13: =IF(EmployeeData3[[#This Row],[Country]]="Canada",1,0) -> 0 | AK13: =IF(EmployeeData3[[#This Row],[Country]]="Germany",1,0) -> 0 | AL13: =IF(EmployeeData3[[#This Row],[Country]]="Ireland",1,0) -> 0 | AM13: =IF(EmployeeData3[[#This Row],[Country]]="Singapore",1,0) -> 0 | AN13: =IF(EmployeeData3[[#This Row],[Country]]="US",1,0) -> 0 | AO13: =IF(EmployeeData3[[#This Row],[Working Arrangement]]="Office",1,0) -> 0 | AP13: =IF(EmployeeData3[[#This Row],[Working Arrangement]]="Remote",1,0) -> 0 | AQ13: ='Logistics Regression'!#REF! + SUMPRODUCT(B13:J13, 'Logistics Regression'!#REF!) -> #REF!
... A1001: E1000 | B1001: =VLOOKUP(EmployeeData3[[#This Row],[Employee ID]],GenderData[#All],2,FALSE) -> Male | C1001: Sales | D1001: Commercial | E1001: UK | F1001: Professional | G1001: 38 | H1001: 14 | I1001: 3.7 | J1001: 1.18 | K1001: Exceeds Expectations | L1001: No | M1001: 17 | N1001: 85 | O1001: 6 | P1001: 1.2 | Q1001: Remote | R1001: No | S1001: 31 | T1001: 0 | U1001: =IF(EmployeeData3[[#This Row],[Gender]]="Female",1,0) -> 0 | V1001: =IF(EmployeeData3[[#This Row],[Performance Rating]]="Needs Improvement",1,0) -> 0 | W1001: =IF(EmployeeData3[[#This Row],[Performance Rating]]="Exceeds Expectations",1,0) -> 1 | X1001: =IF(EmployeeData3[[#This Row],[Performance Rating]]="Outstanding",1,0) -> 0 | Y1001: =IF(EmployeeData3[[#This Row],[Job Level]]="Entry",1,0) -> 0 | Z1001: =IF(EmployeeData3[[#This Row],[Job Level]]="Manager",1,0) -> 0 | AA1001: =IF(EmployeeData3[[#This Row],[Job Level]]="Senior",1,0) -> 0 | AB1001: =IF(EmployeeData3[[#This Row],[Job Level]]="Senior Manager",1,0) -> 0 | AC1001: =IF(EmployeeData3[[#This Row],[Department]]="Claims",1,0) -> 0 | AD1001: =IF(EmployeeData3[[#This Row],[Department]]="Finance",1,0) -> 0 | AE1001: =IF(EmployeeData3[[#This Row],[Department]]="HR",1,0) -> 0 | AF1001: =IF(EmployeeData3[[#This Row],[Department]]="IT",1,0) -> 0 | AG1001: =IF(EmployeeData3[[#This Row],[Department]]="Marketing",1,0) -> 0 | AH1001: =IF(EmployeeData3[[#This Row],[Department]]="Sales",1,0) -> 1 | AI1001: =IF(EmployeeData3[[#This Row],[Department]]="Underwriting",1,0) -> 0 | AJ1001: =IF(EmployeeData3[[#This Row],[Country]]="Canada",1,0) -> 0 | AK1001: =IF(EmployeeData3[[#This Row],[Country]]="Germany",1,0) -> 0 | AL1001: =IF(EmployeeData3[[#This Row],[Country]]="Ireland",1,0) -> 0 | AM1001: =IF(EmployeeData3[[#This Row],[Country]]="Singapore",1,0) -> 0 | AN1001: =IF(EmployeeData3[[#This Row],[Country]]="US",1,0) -> 0 | AO1001: =IF(EmployeeData3[[#This Row],[Working Arrangement]]="Office",1,0) -> 0 | AP1001: =IF(EmployeeData3[[#This Row],[Working Arrangement]]="Remote",1,0) -> 1 | AQ1001: ='Logistics Regression'!#REF! + SUMPRODUCT(B1001:J1001, 'Logistics Regression'!#REF!) -> #REF!

Sheet Logistics Regression
A1: Age | B1: Tenure (Years) | C1: Time in Role (Years) | D1: Compa-Ratio | E1: Promotion in Last 2 Years | F1: Months Since Salary Increase | G1: Engagement Score | H1: Absence Days | I1: Manager Tenure (Years) | J1: Overtime | K1: Training Hours | L1: Gender_Female | M1: Perf_Needs_Improvement | N1: Perf_Exceeds | O1: Perf_Outstanding | P1: Job_Entry | Q1: Job_Manager | R1: Job_Senior | S1: Job_Senior_Manager | T1: Dept_Claims | U1: Dept_Finance | V1: Dept_HR | W1: Dept_IT | X1: Dept_Marketing | Y1: Dept_Sales | Z1: Dept_Underwriting | AA1: Country_Canada | AB1: Country_Germany | AC1: Country_Ireland | AD1: Country_Singapore | AE1: Country_US | AF1: Work_Office | AG1: Work_Remote | AH1: Logit | AI1: Odds | AJ1: Probability | AK1: Log-Liklihood | AL1: Squared Error | AM1: Risk | AN1: Leaver flag | AO1: Dept | AP1: Country | AQ1: Job level | AR1: Leaver flag
A2: 39 | B2: 1.9 | C2: 1.9 | D2: 1.12 | E2: 0 | F2: 19 | G2: 86 | H2: 2 | I2: 5.2 | J2: 0 | K2: 44 | L2: 1 | M2: 0 | N2: 0 | O2: 0 | P2: 0 | Q2: 0 | R2: 0 | S2: 0 | T2: 0 | U2: 0 | V2: 0 | W2: 0 | X2: 0 | Y2: 1 | Z2: 0 | AA2: 0 | AB2: 0 | AC2: 0 | AD2: 0 | AE2: 0 | AF2: 0 | AG2: 1 | AH2: {=$B$1005+SUMPRODUCT(A2:AG2,TRANSPOSE($B$1006:$B$1038))} -> -1.9366531 | AI2: =EXP(EmployeeData36[[#This Row],[Logit]]) -> 0.14418572 | AJ2: =EmployeeData36[[#This Row],[Odds]]/(1+EmployeeData36[[#This Row],[Odds]]) -> 0.12601601 | AK2: =IF(AR2=1,LN(EmployeeData36[[#This Row],[Probability]]),LN(1-EmployeeData36[[#This Row],[Probability]])) -> -0.13469322 | AL2: =(AR2-EmployeeData36[[#This Row],[Probability]])^2 -> 0.015880036 | AM2: =IF(EmployeeData36[[#This Row],[Probability]]<10%,"Low", IF(EmployeeData36[[#This Row],[Probability]]<20%,"Moderate", IF(EmployeeData36[[#This Row],[Probability]]<30%,"High","Very High"))) -> Moderate | AN2: =AR2 -> 0 | AO2: =EmployeeData3[[#This Row],[Department]] -> Sales | AP2: =EmployeeData3[[#This Row],[Country]] -> UK | AQ2: =EmployeeData[[#This Row],[Job Level]] -> Professional | AR2: 0
A3: 32 | B3: 2 | C3: 2 | D3: 0.95 | E3: 0 | F3: 8 | G3: 91 | H3: 2 | I3: 2.8 | J3: 0 | K3: 0 | L3: 0 | M3: 0 | N3: 0 | O3: 0 | P3: 0 | Q3: 0 | R3: 1 | S3: 0 | T3: 1 | U3: 0 | V3: 0 | W3: 0 | X3: 0 | Y3: 0 | Z3: 0 | AA3: 0 | AB3: 1 | AC3: 0 | AD3: 0 | AE3: 0 | AF3: 0 | AG3: 0 | AH3: {=$B$1005+SUMPRODUCT(A3:AG3,TRANSPOSE($B$1006:$B$1038))} -> -3.2579731 | AI3: =EXP(EmployeeData36[[#This Row],[Logit]]) -> 0.038466288 | AJ3: =EmployeeData36[[#This Row],[Odds]]/(1+EmployeeData36[[#This Row],[Odds]]) -> 0.037041441 | AK3: =IF(AR3=1,LN(EmployeeData36[[#This Row],[Probability]]),LN(1-EmployeeData36[[#This Row],[Probability]])) -> -0.037744901 | AL3: =(AR3-EmployeeData36[[#This Row],[Probability]])^2 -> 0.0013720683 | AM3: =IF(EmployeeData36[[#This Row],[Probability]]<10%,"Low", IF(EmployeeData36[[#This Row],[Probability]]<20%,"Moderate", IF(EmployeeData36[[#This Row],[Probability]]<30%,"High","Very High"))) -> Low | AN3: =AR3 -> 0 | AO3: =EmployeeData3[[#This Row],[Department]] -> Claims | AP3: =EmployeeData3[[#This Row],[Country]] -> Germany | AQ3: =EmployeeData[[#This Row],[Job Level]] -> Senior | AR3: 0
A4: 21 | B4: 7.2 | C4: 1.2 | D4: 0.89 | E4: 0 | F4: 31 | G4: 55 | H4: 3 | I4: 0.5 | J4: 1 | K4: 37 | L4: 0 | M4: 0 | N4: 1 | O4: 0 | P4: 0 | Q4: 1 | R4: 0 | S4: 0 | T4: 0 | U4: 0 | V4: 0 | W4: 0 | X4: 1 | Y4: 0 | Z4: 0 | AA4: 0 | AB4: 0 | AC4: 0 | AD4: 0 | AE4: 0 | AF4: 0 | AG4: 1 | AH4: {=$B$1005+SUMPRODUCT(A4:AG4,TRANSPOSE($B$1006:$B$1038))} -> -1.3225325 | AI4: =EXP(EmployeeData36[[#This Row],[Logit]]) -> 0.26645965 | AJ4: =EmployeeData36[[#This Row],[Odds]]/(1+EmployeeData36[[#This Row],[Odds]]) -> 0.21039727 | AK4: =IF(AR4=1,LN(EmployeeData36[[#This Row],[Probability]]),LN(1-EmployeeData36[[#This Row],[Probability]])) -> -0.23622533 | AL4: =(AR4-EmployeeData36[[#This Row],[Probability]])^2 -> 0.044267009 | AM4: =IF(EmployeeData36[[#This Row],[Probability]]<10%,"Low", IF(EmployeeData36[[#This Row],[Probability]]<20%,"Moderate", IF(EmployeeData36[[#This Row],[Probability]]<30%,"High","Very High"))) -> High | AN4: =AR4 -> 0 | AO4: =EmployeeData3[[#This Row],[Department]] -> Marketing | AP4: =EmployeeData3[[#This Row],[Country]] -> UK | AQ4: =EmployeeData[[#This Row],[Job Level]] -> Manager | AR4: 0
A5: 48 | B5: 2 | C5: 2 | D5: 0.99 | E5: 0 | F5: 35 | G5: 78 | H5: 3 | I5: 2.3 | J5: 0 | K5: 27 | L5: 1 | M5: 0 | N5: 1 | O5: 0 | P5: 0 | Q5: 0 | R5: 1 | S5: 0 | T5: 0 | U5: 0 | V5: 0 | W5: 0 | X5: 0 | Y5: 0 | Z5: 0 | AA5: 0 | AB5: 0 | AC5: 0 | AD5: 1 | AE5: 0 | AF5: 0 | AG5: 1 | AH5: {=$B$1005+SUMPRODUCT(A5:AG5,TRANSPOSE($B$1006:$B$1038))} -> -1.6595629 | AI5: =EXP(EmployeeData36[[#This Row],[Logit]]) -> 0.1902221 | AJ5: =EmployeeData36[[#This Row],[Odds]]/(1+EmployeeData36[[#This Row],[Odds]]) -> 0.15982068 | AK5: =IF(AR5=1,LN(EmployeeData36[[#This Row],[Probability]]),LN(1-EmployeeData36[[#This Row],[Probability]])) -> -0.17413993 | AL5: =(AR5-EmployeeData36[[#This Row],[Probability]])^2 -> 0.025542649 | AM5: =IF(EmployeeData36[[#This Row],[Probability]]<10%,"Low", IF(EmployeeData36[[#This Row],[Probability]]<20%,"Moderate", IF(EmployeeData36[[#This Row],[Probability]]<30%,"High","Very High"))) -> Moderate | AN5: =AR5 -> 0 | AO5: =EmployeeData3[[#This Row],[Department]] -> Operations | AP5: =EmployeeData3[[#This Row],[Country]] -> Singapore | AQ5: =EmployeeData[[#This Row],[Job Level]] -> Senior | AR5: 0
A6: 23 | B6: 3.9 | C6: 2.3 | D6: 1.04 | E6: 0 | F6: 16 | G6: 81 | H6: 5 | I6: 4.3 | J6: 1 | K6: 35 | L6: 0 | M6: 0 | N6: 0 | O6: 0 | P6: 0 | Q6: 1 | R6: 0 | S6: 0 | T6: 0 | U6: 1 | V6: 0 | W6: 0 | X6: 0 | Y6: 0 | Z6: 0 | AA6: 0 | AB6: 0 | AC6: 0 | AD6: 0 | AE6: 1 | AF6: 0 | AG6: 0 | AH6: {=$B$1005+SUMPRODUCT(A6:AG6,TRANSPOSE($B$1006:$B$1038))} -> -1.4357491 | AI6: =EXP(EmployeeData36[[#This Row],[Logit]]) -> 0.23793706 | AJ6: =EmployeeData36[[#This Row],[Odds]]/(1+EmployeeData36[[#This Row],[Odds]]) -> 0.19220449 | AK6: =IF(AR6=1,LN(EmployeeData36[[#This Row],[Probability]]),LN(1-EmployeeData36[[#This Row],[Probability]])) -> -0.21344633 | AL6: =(AR6-EmployeeData36[[#This Row],[Probability]])^2 -> 0.036942564 | AM6: =IF(EmployeeData36[[#This Row],[Probability]]<10%,"Low", IF(EmployeeData36[[#This Row],[Probability]]<20%,"Moderate", IF(EmployeeData36[[#This Row],[Probability]]<30%,"High","Very High"))) -> Moderate | AN6: =AR6 -> 0 | AO6: =EmployeeData3[[#This Row],[Department]] -> Finance | AP6: =EmployeeData3[[#This Row],[Country]] -> US | AQ6: =EmployeeData[[#This Row],[Job Level]] -> Manager | AR6: 0
A7: 43 | B7: 2.1 | C7: 1.9 | D7: 0.88 | E7: 0 | F7: 11 | G7: 80 | H7: 9 | I7: 3.4 | J7: 0 | K7: 17 | L7: 1 | M7: 0 | N7: 0 | O7: 0 | P7: 0 | Q7: 0 | R7: 1 | S7: 0 | T7: 0 | U7: 1 | V7: 0 | W7: 0 | X7: 0 | Y7: 0 | Z7: 0 | AA7: 0 | AB7: 1 | AC7: 0 | AD7: 0 | AE7: 0 | AF7: 0 | AG7: 0 | AH7: {=$B$1005+SUMPRODUCT(A7:AG7,TRANSPOSE($B$1006:$B$1038))} -> -2.2526707 | AI7: =EXP(EmployeeData36[[#This Row],[Logit]]) -> 0.10511811 | AJ7: =EmployeeData36[[#This Row],[Odds]]/(1+EmployeeData36[[#This Row],[Odds]]) -> 0.095119341 | AK7: =IF(AR7=1,LN(EmployeeData36[[#This Row],[Probability]]),LN(1-EmployeeData36[[#This Row],[Probability]])) -> -0.099952212 | AL7: =(AR7-EmployeeData36[[#This Row],[Probability]])^2 -> 0.009047689 | AM7: =IF(EmployeeData36[[#This Row],[Probability]]<10%,"Low", IF(EmployeeData36[[#This Row],[Probability]]<20%,"Moderate", IF(EmployeeData36[[#This Row],[Probability]]<30%,"High","Very High"))) -> Low | AN7: =AR7 -> 0 | AO7: =EmployeeData3[[#This Row],[Department]] -> Finance | AP7: =EmployeeData3[[#This Row],[Country]] -> Germany | AQ7: =EmployeeData[[#This Row],[Job Level]] -> Senior | AR7: 0
A8: 38 | B8: 0.3 | C8: 0.3 | D8: 0.97 | E8: 0 | F8: 14 | G8: 78 | H8: 2 | I8: 3.7 | J8: 1 | K8: 3 | L8: 1 | M8: 0 | N8: 0 | O8: 0 | P8: 0 | Q8: 0 | R8: 1 | S8: 0 | T8: 0 | U8: 0 | V8: 0 | W8: 1 | X8: 0 | Y8: 0 | Z8: 0 | AA8: 0 | AB8: 0 | AC8: 0 | AD8: 0 | AE8: 0 | AF8: 1 | AG8: 0 | AH8: {=$B$1005+SUMPRODUCT(A8:AG8,TRANSPOSE($B$1006:$B$1038))} -> -2.0195501 | AI8: =EXP(EmployeeData36[[#This Row],[Logit]]) -> 0.13271517 | AJ8: =EmployeeData36[[#This Row],[Odds]]/(1+EmployeeData36[[#This Row],[Odds]]) -> 0.11716552 | AK8: =IF(AR8=1,LN(EmployeeData36[[#This Row],[Probability]]),LN(1-EmployeeData36[[#This Row],[Probability]])) -> -0.12461755 | AL8: =(AR8-EmployeeData36[[#This Row],[Probability]])^2 -> 0.01372776 | AM8: =IF(EmployeeData36[[#This Row],[Probability]]<10%,"Low", IF(EmployeeData36[[#This Row],[Probability]]<20%,"Moderate", IF(EmployeeData36[[#This Row],[Probability]]<30%,"High","Very High"))) -> Moderate | AN8: =AR8 -> 0 | AO8: =EmployeeData3[[#This Row],[Department]] -> IT | AP8: =EmployeeData3[[#This Row],[Country]] -> UK | AQ8: =EmployeeData[[#This Row],[Job Level]] -> Senior | AR8: 0
A9: 57 | B9: 7 | C9: 3.1 | D9: 1 | E9: 1 | F9: 22 | G9: 51 | H9: 9 | I9: 4.6 | J9: 0 | K9: 31 | L9: 0 | M9: 1 | N9: 0 | O9: 0 | P9: 0 | Q9: 1 | R9: 0 | S9: 0 | T9: 0 | U9: 0 | V9: 0 | W9: 0 | X9: 0 | Y9: 0 | Z9: 1 | AA9: 0 | AB9: 0 | AC9: 0 | AD9: 0 | AE9: 0 | AF9: 0 | AG9: 0 | AH9: {=$B$1005+SUMPRODUCT(A9:AG9,TRANSPOSE($B$1006:$B$1038))} -> -2.4505125 | AI9: =EXP(EmployeeData36[[#This Row],[Logit]]) -> 0.086249368 | AJ9: =EmployeeData36[[#This Row],[Odds]]/(1+EmployeeData36[[#This Row],[Odds]]) -> 0.079401076 | AK9: =IF(AR9=1,LN(EmployeeData36[[#This Row],[Probability]]),LN(1-EmployeeData36[[#This Row],[Probability]])) -> -0.082730816 | AL9: =(AR9-EmployeeData36[[#This Row],[Probability]])^2 -> 0.0063045308 | AM9: =IF(EmployeeData36[[#This Row],[Probability]]<10%,"Low", IF(EmployeeData36[[#This Row],[Probability]]<20%,"Moderate", IF(EmployeeData36[[#This Row],[Probability]]<30%,"High","Very High"))) -> Low | AN9: =AR9 -> 0 | AO9: =EmployeeData3[[#This Row],[Department]] -> Underwriting | AP9: =EmployeeData3[[#This Row],[Country]] -> UK | AQ9: =EmployeeData[[#This Row],[Job Level]] -> Manager | AR9: 0
A10: 47 | B10: 4.1 | C10: 4.1 | D10: 1.01 | E10: 0 | F10: 28 | G10: 63 | H10: 8 | I10: 1.1 | J10: 1 | K10: 13 | L10: 0 | M10: 0 | N10: 1 | O10: 0 | P10: 0 | Q10: 0 | R10: 0 | S10: 0 | T10: 0 | U10: 0 | V10: 0 | W10: 0 | X10: 0 | Y10: 0 | Z10: 0 | AA10: 1 | AB10: 0 | AC10: 0 | AD10: 0 | AE10: 0 | AF10: 0 | AG10: 0 | AH10: {=$B$1005+SUMPRODUCT(A10:AG10,TRANSPOSE($B$1006:$B$1038))} -> 0.037326494 | AI10: =EXP(EmployeeData36[[#This Row],[Logit]]) -> 1.0380319 | AJ10: =EmployeeData36[[#This Row],[Odds]]/(1+EmployeeData36[[#This Row],[Odds]]) -> 0.50933054 | AK10: =IF(AR10=1,LN(EmployeeData36[[#This Row],[Probability]]),LN(1-EmployeeData36[[#This Row],[Probability]])) -> -0.71198458 | AL10: =(AR10-EmployeeData36[[#This Row],[Probability]])^2 -> 0.2594176 | AM10: =IF(EmployeeData36[[#This Row],[Probability]]<10%,"Low", IF(EmployeeData36[[#This Row],[Probability]]<20%,"Moderate", IF(EmployeeData36[[#This Row],[Probability]]<30%,"High","Very High"))) -> Very High | AN10: =AR10 -> 0 | AO10: =EmployeeData3[[#This Row],[Department]] -> Operations | AP10: =EmployeeData3[[#This Row],[Country]] -> Canada | AQ10: =EmployeeData[[#This Row],[Job Level]] -> Professional | AR10: 0
A11: 33 | B11: 5.6 | C11: 5.6 | D11: 1.01 | E11: 0 | F11: 21 | G11: 55 | H11: 8 | I11: 4.7 | J11: 0 | K11: 7 | L11: 0 | M11: 0 | N11: 0 | O11: 0 | P11: 0 | Q11: 0 | R11: 0 | S11: 0 | T11: 0 | U11: 0 | V11: 0 | W11: 0 | X11: 1 | Y11: 0 | Z11: 0 | AA11: 0 | AB11: 0 | AC11: 0 | AD11: 0 | AE11: 1 | AF11: 0 | AG11: 0 | AH11: {=$B$1005+SUMPRODUCT(A11:AG11,TRANSPOSE($B$1006:$B$1038))} -> -1.0052077 | AI11: =EXP(EmployeeData36[[#This Row],[Logit]]) -> 0.36596861 | AJ11: =EmployeeData36[[#This Row],[Odds]]/(1+EmployeeData36[[#This Row],[Odds]]) -> 0.26791876 | AK11: =IF(AR11=1,LN(EmployeeData36[[#This Row],[Probability]]),LN(1-EmployeeData36[[#This Row],[Probability]])) -> -1.3170715 | AL11: =(AR11-EmployeeData36[[#This Row],[Probability]])^2 -> 0.53594295 | AM11: =IF(EmployeeData36[[#This Row],[Probability]]<10%,"Low", IF(EmployeeData36[[#This Row],[Probability]]<20%,"Moderate", IF(EmployeeData36[[#This Row],[Probability]]<30%,"High","Very High"))) -> High | AN11: =AR11 -> 1 | AO11: =EmployeeData3[[#This Row],[Department]] -> Marketing | AP11: =EmployeeData3[[#This Row],[Country]] -> US | AQ11: =EmployeeData[[#This Row],[Job Level]] -> Professional | AR11: 1
A12: 32 | B12: 0.9 | C12: 0.9 | D12: 1.03 | E12: 0 | F12: 17 | G12: 70 | H12: 5 | I12: 8.4 | J12: 0 | K12: 8 | L12: 1 | M12: 0 | N12: 1 | O12: 0 | P12: 0 | Q12: 0 | R12: 0 | S12: 0 | T12: 0 | U12: 0 | V12: 0 | W12: 1 | X12: 0 | Y12: 0 | Z12: 0 | AA12: 0 | AB12: 0 | AC12: 0 | AD12: 0 | AE12: 0 | AF12: 0 | AG12: 0 | AH12: {=$B$1005+SUMPRODUCT(A12:AG12,TRANSPOSE($B$1006:$B$1038))} -> -1.6648464 | AI12: =EXP(EmployeeData36[[#This Row],[Logit]]) -> 0.18921972 | AJ12: =EmployeeData36[[#This Row],[Odds]]/(1+EmployeeData36[[#This Row],[Odds]]) -> 0.1591125 | AK12: =IF(AR12=1,LN(EmployeeData36[[#This Row],[Probability]]),LN(1-EmployeeData36[[#This Row],[Probability]])) -> -1.8381438 | AL12: =(AR12-EmployeeData36[[#This Row],[Probability]])^2 -> 0.70709179 | AM12: =IF(EmployeeData36[[#This Row],[Probability]]<10%,"Low", IF(EmployeeData36[[#This Row],[Probability]]<20%,"Moderate", IF(EmployeeData36[[#This Row],[Probability]]<30%,"High","Very High"))) -> Moderate | AN12: =AR12 -> 1 | AO12: =EmployeeData3[[#This Row],[Department]] -> IT | AP12: =EmployeeData3[[#This Row],[Country]] -> UK | AQ12: =EmployeeData[[#This Row],[Job Level]] -> Professional | AR12: 1
A13: 52 | B13: 2.6 | C13: 2.4 | D13: 0.91 | E13: 0 | F13: 29 | G13: 80 | H13: 2 | I13: 2.1 | J13: 0 | K13: 31 | L13: 1 | M13: 0 | N13: 1 | O13: 0 | P13: 0 | Q13: 0 | R13: 0 | S13: 1 | T13: 1 | U13: 0 | V13: 0 | W13: 0 | X13: 0 | Y13: 0 | Z13: 0 | AA13: 0 | AB13: 0 | AC13: 0 | AD13: 0 | AE13: 0 | AF13: 0 | AG13: 0 | AH13: {=$B$1005+SUMPRODUCT(A13:AG13,TRANSPOSE($B$1006:$B$1038))} -> -1.8260108 | AI13: =EXP(EmployeeData36[[#This Row],[Logit]]) -> 0.16105477 | AJ13: =EmployeeData36[[#This Row],[Odds]]/(1+EmployeeData36[[#This Row],[Odds]]) -> 0.13871419 | AK13: =IF(AR13=1,LN(EmployeeData36[[#This Row],[Probability]]),LN(1-EmployeeData36[[#This Row],[Probability]])) -> -0.14932888 | AL13: =(AR13-EmployeeData36[[#This Row],[Probability]])^2 -> 0.019241627 | AM13: =IF(EmployeeData36[[#This Row],[Probability]]<10%,"Low", IF(EmployeeData36[[#This Row],[Probability]]<20%,"Moderate", IF(EmployeeData36[[#This Row],[Probability]]<30%,"High","Very High"))) -> Moderate | AN13: =AR13 -> 0 | AO13: =EmployeeData3[[#This Row],[Department]] -> Claims | AP13: =EmployeeData3[[#This Row],[Country]] -> UK | AQ13: =EmployeeData[[#This Row],[Job Level]] -> Senior Manager | AR13: 0
... A1001: 38 | B1001: 14 | C1001: 3.7 | D1001: 1.18 | E1001: 0 | F1001: 17 | G1001: 85 | H1001: 6 | I1001: 1.2 | J1001: 0 | K1001: 31 | L1001: 0 | M1001: 0 | N1001: 1 | O1001: 0 | P1001: 0 | Q1001: 0 | R1001: 0 | S1001: 0 | T1001: 0 | U1001: 0 | V1001: 0 | W1001: 0 | X1001: 0 | Y1001: 1 | Z1001: 0 | AA1001: 0 | AB1001: 0 | AC1001: 0 | AD1001: 0 | AE1001: 0 | AF1001: 0 | AG1001: 1 | AH1001: {=$B$1005+SUMPRODUCT(A1001:AG1001,TRANSPOSE($B$1006:$B$1038))} -> -3.0683566 | AI1001: =EXP(EmployeeData36[[#This Row],[Logit]]) -> 0.046497506 | AJ1001: =EmployeeData36[[#This Row],[Odds]]/(1+EmployeeData36[[#This Row],[Odds]]) -> 0.04443155 | AK1001: =IF(AR1001=1,LN(EmployeeData36[[#This Row],[Probability]]),LN(1-EmployeeData36[[#This Row],[Probability]])) -> -0.04544888 | AL1001: =(AR1001-EmployeeData36[[#This Row],[Probability]])^2 -> 0.0019741626 | AM1001: =IF(EmployeeData36[[#This Row],[Probability]]<10%,"Low", IF(EmployeeData36[[#This Row],[Probability]]<20%,"Moderate", IF(EmployeeData36[[#This Row],[Probability]]<30%,"High","Very High"))) -> Low | AN1001: =AR1001 -> 0 | AO1001: =EmployeeData3[[#This Row],[Department]] -> Sales | AP1001: =EmployeeData3[[#This Row],[Country]] -> UK | AQ1001: =EmployeeData[[#This Row],[Job Level]] -> Professional | AR1001: 0
AK1002: =SUM(EmployeeData36[Log-Liklihood]) -> -374.36072 | AL1002: =AVERAGE(EmployeeData36[Squared Error]) -> 0.11272437
A1005: Intercept | B1005: -0.76828813
A1006: Age | B1006: -0.0092002473
A1007: Tenure (Years) | B1007: -0.070416045
A1008: Time in Role (Years) | B1008: 0.21701153
A1009: Compa-Ratio | B1009: 0.3310528
A1010: Promotion in Last 2 Years | B1010: -0.80353439
A1011: Months Since Salary Increase | B1011: 0.020995385
A1012: Engagement Score | B1012: -0.03333389
A1013: Absence Days | B1013: 0.019687579
A1014: Manager Tenure (Years) | B1014: 0.031909214
A1015: Overtime | B1015: 0.57616316
A1016: Training Hours | B1016: 0.0056620579
... A1038: Work_Remote | B1038: 0.0019107884

Sheet Prediction Workflow
A1: Step 1 — Define the prediction target
A3: Our target will be:
A5: Leaver flag
A7: 1 = employee left
A8: 0 = employee remained
A10: So the modelling question becomes:
A12: “Based on an employee's characteristics and circumstances, can we estimate their likelihood of attrition?”
A14: Step 2 — Select the predictor variables
A16: Your dataset gives us a strong set of potential predictors:
A18: Predictor | B18: Why it could matter
A19: Engagement Score / Band | B19: Employee sentiment and connection
A20: Compa-Ratio / Band | B20: Pay positioning
A21: Months Since Salary Increase | B21: Reward progression
A22: Promotion in Last 2 Years | B22: Career progression
A23: Overtime | B23: Workload/work-life balance
A24: Tenure | B24: Employee lifecycle
A25: Time in Role | B25: Career stagnation
A26: Job Level | B26: Seniority
A27: Department | B27: Organisational differences
A28: Gender | B28: DEI/retention differences
A29: Country | B29: Geographic differences
... A35: Training Hours | B35: Development opportunity
A37: However, we shouldn't put every variable into the model automatically. Some are closely related or potentially redundant. We'll make that decision systematically.
A39: One important modelling rule
A41: We must make sure the predictors represent information that would have been available before the employee left.
A43: For example, Leaver flag is our outcome. We don't want to accidentally use anything that was determined because someone left, because that would create data leakage and make the model look better than it really is.
A47: What we'll build
A49: The predictive section will ultimately look something like:
A51: Employee Data → Prepare Variables → Build Model → Validate Model → Risk Score → Risk Bands → Business Actions
A53: And we'll evaluate whether the model actually identifies higher-risk employees rather than simply producing a score.
A55: For an interview-quality People Analytics project, I'd like us to eventually show:
A57: Probability of attrition
A58: Low / Medium / High risk
A59: Key factors associated with risk
... A68: Before modelling, I want to inspect the actual distributions and coding of the variables in your latest dataset — particularly the 149 leavers vs 851 non-leavers and the categorical fields.

Sheet Gender Data
A1: Employee ID | B1: Gender
A2: E0001 | B2: Female
A3: E0002 | B3: Male
A4: E0003 | B4: Male
A5: E0004 | B5: Female
A6: E0005 | B6: Male
A7: E0006 | B7: Female
A8: E0007 | B8: Female
A9: E0008 | B9: Male
A10: E0009 | B10: Male
A11: E0010 | B11: Male
A12: E0011 | B12: Female
... A1001: E1000 | B1001: Male

Sheet Employee Data
A1: Employee ID | B1: Gender | C1: Department | D1: Business Unit | E1: Country | F1: Job Level | G1: Age | H1: Age group | I1: Tenure (Years) | J1: Tenure Band | K1: Time in Role (Years) | L1: Annual Salary | M1: Compa-Ratio | N1: Compa-Ratio Band | O1: Performance Rating | P1: Promotion in Last 2 Years | Q1: Months Since Salary Increase | R1: Salary increase recency | S1: Engagement Score | T1: Engagement band | U1: Absence Days | V1: Manager Tenure (Years) | W1: Working Arrangement | X1: Overtime | Y1: Training Hours | Z1: Attrition | AA1: Leaver flag
A2: E0001 | B2: =VLOOKUP(EmployeeData[[#This Row],[Employee ID]],GenderData[#All],2,FALSE) -> Female | C2: Sales | D2: Commercial | E2: UK | F2: Professional | G2: 39 | H2: =IF(EmployeeData[[#This Row],[Age]]<=31,"18-31",IF(EmployeeData[[#This Row],[Age]]<=45,"32-45",IF(EmployeeData[[#This Row],[Age]]<=59,"46-59",IF(EmployeeData[[#This Row],[Age]]<=73,"60-73")))) -> 32-45 | I2: 1.9 | J2: =IF(EmployeeData[[#This Row],[Tenure (Years)]]<1,"Less than 1 year",IF(EmployeeData[[#This Row],[Tenure (Years)]]<2,"1-<2 years",IF(EmployeeData[[#This Row],[Tenure (Years)]]<5,"2-<5 years",IF(EmployeeData[[#This Row],[Tenure (Years)]]<10,"5-<10 years",IF(EmployeeData[[#This Row],[Tenure (Years)]]<15,"10-<15 years","16+ years"))))) -> 1-<2 years | K2: 1.9 | L2: 54100 | M2: 1.12 | N2: =IF(EmployeeData[[#This Row],[Compa-Ratio]]<0.85,"less than 0.85",IF(EmployeeData[[#This Row],[Compa-Ratio]]<1,"0.85-<1.00",IF(EmployeeData[[#This Row],[Compa-Ratio]]<1.15,"1.00-<1.15",IF(EmployeeData[[#This Row],[Compa-Ratio]]>=1.15,"1.15+")))) -> 1.00-<1.15 | O2: Meets Expectations | P2: No | Q2: 19 | R2: =IF(EmployeeData[[#This Row],[Months Since Salary Increase]]<6,"<6 months",IF(EmployeeData[[#This Row],[Months Since Salary Increase]]<=12,"6-12 months",IF(EmployeeData[[#This Row],[Months Since Salary Increase]]<=24,"13-24 months", IF(EmployeeData[[#This Row],[Months Since Salary Increase]]>24,"24+ months")))) -> 13-24 months | S2: 86 | T2: {=_xlfn.IFS(EmployeeData[[#This Row],[Engagement Score]]<50,"Low",EmployeeData[[#This Row],[Engagement Score]] <70,"Moderate", EmployeeData[[#This Row],[Engagement Score]]<85,"High",TRUE,"Very high")} -> Very high | U2: 2 | V2: 5.2 | W2: Remote | X2: No | Y2: 44 | Z2: No | AA2: =IF(EmployeeData[[#This Row],[Attrition]]="Yes",1,0) -> 0
A3: E0002 | B3: =VLOOKUP(EmployeeData[[#This Row],[Employee ID]],GenderData[#All],2,FALSE) -> Male | C3: Claims | D3: Insurance | E3: Germany | F3: Senior | G3: 32 | H3: =IF(EmployeeData[[#This Row],[Age]]<=31,"18-31",IF(EmployeeData[[#This Row],[Age]]<=45,"32-45",IF(EmployeeData[[#This Row],[Age]]<=59,"46-59",IF(EmployeeData[[#This Row],[Age]]<=73,"60-73")))) -> 32-45 | I3: 2 | J3: =IF(EmployeeData[[#This Row],[Tenure (Years)]]<1,"Less than 1 year",IF(EmployeeData[[#This Row],[Tenure (Years)]]<2,"1-<2 years",IF(EmployeeData[[#This Row],[Tenure (Years)]]<5,"2-<5 years",IF(EmployeeData[[#This Row],[Tenure (Years)]]<10,"5-<10 years",IF(EmployeeData[[#This Row],[Tenure (Years)]]<15,"10-<15 years","16+ years"))))) -> 2-<5 years | K3: 2 | L3: 58500 | M3: 0.95 | N3: =IF(EmployeeData[[#This Row],[Compa-Ratio]]<0.85,"less than 0.85",IF(EmployeeData[[#This Row],[Compa-Ratio]]<1,"0.85-<1.00",IF(EmployeeData[[#This Row],[Compa-Ratio]]<1.15,"1.00-<1.15",IF(EmployeeData[[#This Row],[Compa-Ratio]]>=1.15,"1.15+")))) -> 0.85-<1.00 | O3: Meets Expectations | P3: No | Q3: 8 | R3: =IF(EmployeeData[[#This Row],[Months Since Salary Increase]]<6,"<6 months",IF(EmployeeData[[#This Row],[Months Since Salary Increase]]<=12,"6-12 months",IF(EmployeeData[[#This Row],[Months Since Salary Increase]]<=24,"13-24 months", IF(EmployeeData[[#This Row],[Months Since Salary Increase]]>24,"24+ months")))) -> 6-12 months | S3: 91 | T3: {=_xlfn.IFS(EmployeeData[[#This Row],[Engagement Score]]<50,"Low",EmployeeData[[#This Row],[Engagement Score]] <70,"Moderate", EmployeeData[[#This Row],[Engagement Score]]<85,"High",TRUE,"Very high")} -> Very high | U3: 2 | V3: 2.8 | W3: Hybrid | X3: No | Y3: 0 | Z3: No | AA3: =IF(EmployeeData[[#This Row],[Attrition]]="Yes",1,0) -> 0
A4: E0003 | B4: =VLOOKUP(EmployeeData[[#This Row],[Employee ID]],GenderData[#All],2,FALSE) -> Male | C4: Marketing | D4: Commercial | E4: UK | F4: Manager | G4: 21 | H4: =IF(EmployeeData[[#This Row],[Age]]<=31,"18-31",IF(EmployeeData[[#This Row],[Age]]<=45,"32-45",IF(EmployeeData[[#This Row],[Age]]<=59,"46-59",IF(EmployeeData[[#This Row],[Age]]<=73,"60-73")))) -> 18-31 | I4: 7.2 | J4: =IF(EmployeeData[[#This Row],[Tenure (Years)]]<1,"Less than 1 year",IF(EmployeeData[[#This Row],[Tenure (Years)]]<2,"1-<2 years",IF(EmployeeData[[#This Row],[Tenure (Years)]]<5,"2-<5 years",IF(EmployeeData[[#This Row],[Tenure (Years)]]<10,"5-<10 years",IF(EmployeeData[[#This Row],[Tenure (Years)]]<15,"10-<15 years","16+ years"))))) -> 5-<10 years | K4: 1.2 | L4: 69200 | M4: 0.89 | N4: =IF(EmployeeData[[#This Row],[Compa-Ratio]]<0.85,"less than 0.85",IF(EmployeeData[[#This Row],[Compa-Ratio]]<1,"0.85-<1.00",IF(EmployeeData[[#This Row],[Compa-Ratio]]<1.15,"1.00-<1.15",IF(EmployeeData[[#This Row],[Compa-Ratio]]>=1.15,"1.15+")))) -> 0.85-<1.00 | O4: Exceeds Expectations | P4: No | Q4: 31 | R4: =IF(EmployeeData[[#This Row],[Months Since Salary Increase]]<6,"<6 months",IF(EmployeeData[[#This Row],[Months Since Salary Increase]]<=12,"6-12 months",IF(EmployeeData[[#This Row],[Months Since Salary Increase]]<=24,"13-24 months", IF(EmployeeData[[#This Row],[Months Since Salary Increase]]>24,"24+ months")))) -> 24+ months | S4: 55 | T4: {=_xlfn.IFS(EmployeeData[[#This Row],[Engagement Score]]<50,"Low",EmployeeData[[#This Row],[Engagement Score]] <70,"Moderate", EmployeeData[[#This Row],[Engagement Score]]<85,"High",TRUE,"Very high")} -> Moderate | U4: 3 | V4: 0.5 | W4: Remote | X4: Yes | Y4: 37 | Z4: No | AA4: =IF(EmployeeData[[#This Row],[Attrition]]="Yes",1,0) -> 0
A5: E0004 | B5: =VLOOKUP(EmployeeData[[#This Row],[Employee ID]],GenderData[#All],2,FALSE) -> Female | C5: Operations | D5: Operations | E5: Singapore | F5: Senior | G5: 48 | H5: =IF(EmployeeData[[#This Row],[Age]]<=31,"18-31",IF(EmployeeData[[#This Row],[Age]]<=45,"32-45",IF(EmployeeData[[#This Row],[Age]]<=59,"46-59",IF(EmployeeData[[#This Row],[Age]]<=73,"60-73")))) -> 46-59 | I5: 2 | J5: =IF(EmployeeData[[#This Row],[Tenure (Years)]]<1,"Less than 1 year",IF(EmployeeData[[#This Row],[Tenure (Years)]]<2,"1-<2 years",IF(EmployeeData[[#This Row],[Tenure (Years)]]<5,"2-<5 years",IF(EmployeeData[[#This Row],[Tenure (Years)]]<10,"5-<10 years",IF(EmployeeData[[#This Row],[Tenure (Years)]]<15,"10-<15 years","16+ years"))))) -> 2-<5 years | K5: 2 | L5: 62400 | M5: 0.99 | N5: =IF(EmployeeData[[#This Row],[Compa-Ratio]]<0.85,"less than 0.85",IF(EmployeeData[[#This Row],[Compa-Ratio]]<1,"0.85-<1.00",IF(EmployeeData[[#This Row],[Compa-Ratio]]<1.15,"1.00-<1.15",IF(EmployeeData[[#This Row],[Compa-Ratio]]>=1.15,"1.15+")))) -> 0.85-<1.00 | O5: Exceeds Expectations | P5: No | Q5: 35 | R5: =IF(EmployeeData[[#This Row],[Months Since Salary Increase]]<6,"<6 months",IF(EmployeeData[[#This Row],[Months Since Salary Increase]]<=12,"6-12 months",IF(EmployeeData[[#This Row],[Months Since Salary Increase]]<=24,"13-24 months", IF(EmployeeData[[#This Row],[Months Since Salary Increase]]>24,"24+ months")))) -> 24+ months | S5: 78 | T5: {=_xlfn.IFS(EmployeeData[[#This Row],[Engagement Score]]<50,"Low",EmployeeData[[#This Row],[Engagement Score]] <70,"Moderate", EmployeeData[[#This Row],[Engagement Score]]<85,"High",TRUE,"Very high")} -> High | U5: 3 | V5: 2.3 | W5: Remote | X5: No | Y5: 27 | Z5: No | AA5: =IF(EmployeeData[[#This Row],[Attrition]]="Yes",1,0) -> 0
A6: E0005 | B6: =VLOOKUP(EmployeeData[[#This Row],[Employee ID]],GenderData[#All],2,FALSE) -> Male | C6: Finance | D6: Corporate | E6: US | F6: Manager | G6: 23 | H6: =IF(EmployeeData[[#This Row],[Age]]<=31,"18-31",IF(EmployeeData[[#This Row],[Age]]<=45,"32-45",IF(EmployeeData[[#This Row],[Age]]<=59,"46-59",IF(EmployeeData[[#This Row],[Age]]<=73,"60-73")))) -> 18-31 | I6: 3.9 | J6: =IF(EmployeeData[[#This Row],[Tenure (Years)]]<1,"Less than 1 year",IF(EmployeeData[[#This Row],[Tenure (Years)]]<2,"1-<2 years",IF(EmployeeData[[#This Row],[Tenure (Years)]]<5,"2-<5 years",IF(EmployeeData[[#This Row],[Tenure (Years)]]<10,"5-<10 years",IF(EmployeeData[[#This Row],[Tenure (Years)]]<15,"10-<15 years","16+ years"))))) -> 2-<5 years | K6: 2.3 | L6: 78900 | M6: 1.04 | N6: =IF(EmployeeData[[#This Row],[Compa-Ratio]]<0.85,"less than 0.85",IF(EmployeeData[[#This Row],[Compa-Ratio]]<1,"0.85-<1.00",IF(EmployeeData[[#This Row],[Compa-Ratio]]<1.15,"1.00-<1.15",IF(EmployeeData[[#This Row],[Compa-Ratio]]>=1.15,"1.15+")))) -> 1.00-<1.15 | O6: Meets Expectations | P6: No | Q6: 16 | R6: =IF(EmployeeData[[#This Row],[Months Since Salary Increase]]<6,"<6 months",IF(EmployeeData[[#This Row],[Months Since Salary Increase]]<=12,"6-12 months",IF(EmployeeData[[#This Row],[Months Since Salary Increase]]<=24,"13-24 months", IF(EmployeeData[[#This Row],[Months Since Salary Increase]]>24,"24+ months")))) -> 13-24 months | S6: 81 | T6: {=_xlfn.IFS(EmployeeData[[#This Row],[Engagement Score]]<50,"Low",EmployeeData[[#This Row],[Engagement Score]] <70,"Moderate", EmployeeData[[#This Row],[Engagement Score]]<85,"High",TRUE,"Very high")} -> High | U6: 5 | V6: 4.3 | W6: Hybrid | X6: Yes | Y6: 35 | Z6: No | AA6: =IF(EmployeeData[[#This Row],[Attrition]]="Yes",1,0) -> 0
A7: E0006 | B7: =VLOOKUP(EmployeeData[[#This Row],[Employee ID]],GenderData[#All],2,FALSE) -> Female | C7: Finance | D7: Corporate | E7: Germany | F7: Senior | G7: 43 | H7: =IF(EmployeeData[[#This Row],[Age]]<=31,"18-31",IF(EmployeeData[[#This Row],[Age]]<=45,"32-45",IF(EmployeeData[[#This Row],[Age]]<=59,"46-59",IF(EmployeeData[[#This Row],[Age]]<=73,"60-73")))) -> 32-45 | I7: 2.1 | J7: =IF(EmployeeData[[#This Row],[Tenure (Years)]]<1,"Less than 1 year",IF(EmployeeData[[#This Row],[Tenure (Years)]]<2,"1-<2 years",IF(EmployeeData[[#This Row],[Tenure (Years)]]<5,"2-<5 years",IF(EmployeeData[[#This Row],[Tenure (Years)]]<10,"5-<10 years",IF(EmployeeData[[#This Row],[Tenure (Years)]]<15,"10-<15 years","16+ years"))))) -> 2-<5 years | K7: 1.9 | L7: 54600 | M7: 0.88 | N7: =IF(EmployeeData[[#This Row],[Compa-Ratio]]<0.85,"less than 0.85",IF(EmployeeData[[#This Row],[Compa-Ratio]]<1,"0.85-<1.00",IF(EmployeeData[[#This Row],[Compa-Ratio]]<1.15,"1.00-<1.15",IF(EmployeeData[[#This Row],[Compa-Ratio]]>=1.15,"1.15+")))) -> 0.85-<1.00 | O7: Meets Expectations | P7: No | Q7: 11 | R7: =IF(EmployeeData[[#This Row],[Months Since Salary Increase]]<6,"<6 months",IF(EmployeeData[[#This Row],[Months Since Salary Increase]]<=12,"6-12 months",IF(EmployeeData[[#This Row],[Months Since Salary Increase]]<=24,"13-24 months", IF(EmployeeData[[#This Row],[Months Since Salary Increase]]>24,"24+ months")))) -> 6-12 months | S7: 80 | T7: {=_xlfn.IFS(EmployeeData[[#This Row],[Engagement Score]]<50,"Low",EmployeeData[[#This Row],[Engagement Score]] <70,"Moderate", EmployeeData[[#This Row],[Engagement Score]]<85,"High",TRUE,"Very high")} -> High | U7: 9 | V7: 3.4 | W7: Hybrid | X7: No | Y7: 17 | Z7: No | AA7: =IF(EmployeeData[[#This Row],[Attrition]]="Yes",1,0) -> 0
A8: E0007 | B8: =VLOOKUP(EmployeeData[[#This Row],[Employee ID]],GenderData[#All],2,FALSE) -> Female | C8: IT | D8: Technology | E8: UK | F8: Senior | G8: 38 | H8: =IF(EmployeeData[[#This Row],[Age]]<=31,"18-31",IF(EmployeeData[[#This Row],[Age]]<=45,"32-45",IF(EmployeeData[[#This Row],[Age]]<=59,"46-59",IF(EmployeeData[[#This Row],[Age]]<=73,"60-73")))) -> 32-45 | I8: 0.3 | J8: =IF(EmployeeData[[#This Row],[Tenure (Years)]]<1,"Less than 1 year",IF(EmployeeData[[#This Row],[Tenure (Years)]]<2,"1-<2 years",IF(EmployeeData[[#This Row],[Tenure (Years)]]<5,"2-<5 years",IF(EmployeeData[[#This Row],[Tenure (Years)]]<10,"5-<10 years",IF(EmployeeData[[#This Row],[Tenure (Years)]]<15,"10-<15 years","16+ years"))))) -> Less than 1 year | K8: 0.3 | L8: 60800 | M8: 0.97 | N8: =IF(EmployeeData[[#This Row],[Compa-Ratio]]<0.85,"less than 0.85",IF(EmployeeData[[#This Row],[Compa-Ratio]]<1,"0.85-<1.00",IF(EmployeeData[[#This Row],[Compa-Ratio]]<1.15,"1.00-<1.15",IF(EmployeeData[[#This Row],[Compa-Ratio]]>=1.15,"1.15+")))) -> 0.85-<1.00 | O8: Meets Expectations | P8: No | Q8: 14 | R8: =IF(EmployeeData[[#This Row],[Months Since Salary Increase]]<6,"<6 months",IF(EmployeeData[[#This Row],[Months Since Salary Increase]]<=12,"6-12 months",IF(EmployeeData[[#This Row],[Months Since Salary Increase]]<=24,"13-24 months", IF(EmployeeData[[#This Row],[Months Since Salary Increase]]>24,"24+ months")))) -> 13-24 months | S8: 78 | T8: {=_xlfn.IFS(EmployeeData[[#This Row],[Engagement Score]]<50,"Low",EmployeeData[[#This Row],[Engagement Score]] <70,"Moderate", EmployeeData[[#This Row],[Engagement Score]]<85,"High",TRUE,"Very high")} -> High | U8: 2 | V8: 3.7 | W8: Office | X8: Yes | Y8: 3 | Z8: No | AA8: =IF(EmployeeData[[#This Row],[Attrition]]="Yes",1,0) -> 0
A9: E0008 | B9: =VLOOKUP(EmployeeData[[#This Row],[Employee ID]],GenderData[#All],2,FALSE) -> Male | C9: Underwriting | D9: Insurance | E9: UK | F9: Manager | G9: 57 | H9: =IF(EmployeeData[[#This Row],[Age]]<=31,"18-31",IF(EmployeeData[[#This Row],[Age]]<=45,"32-45",IF(EmployeeData[[#This Row],[Age]]<=59,"46-59",IF(EmployeeData[[#This Row],[Age]]<=73,"60-73")))) -> 46-59 | I9: 7 | J9: =IF(EmployeeData[[#This Row],[Tenure (Years)]]<1,"Less than 1 year",IF(EmployeeData[[#This Row],[Tenure (Years)]]<2,"1-<2 years",IF(EmployeeData[[#This Row],[Tenure (Years)]]<5,"2-<5 years",IF(EmployeeData[[#This Row],[Tenure (Years)]]<10,"5-<10 years",IF(EmployeeData[[#This Row],[Tenure (Years)]]<15,"10-<15 years","16+ years"))))) -> 5-<10 years | K9: 3.1 | L9: 81400 | M9: 1 | N9: =IF(EmployeeData[[#This Row],[Compa-Ratio]]<0.85,"less than 0.85",IF(EmployeeData[[#This Row],[Compa-Ratio]]<1,"0.85-<1.00",IF(EmployeeData[[#This Row],[Compa-Ratio]]<1.15,"1.00-<1.15",IF(EmployeeData[[#This Row],[Compa-Ratio]]>=1.15,"1.15+")))) -> 1.00-<1.15 | O9: Needs Improvement | P9: Yes | Q9: 22 | R9: =IF(EmployeeData[[#This Row],[Months Since Salary Increase]]<6,"<6 months",IF(EmployeeData[[#This Row],[Months Since Salary Increase]]<=12,"6-12 months",IF(EmployeeData[[#This Row],[Months Since Salary Increase]]<=24,"13-24 months", IF(EmployeeData[[#This Row],[Months Since Salary Increase]]>24,"24+ months")))) -> 13-24 months | S9: 51 | T9: {=_xlfn.IFS(EmployeeData[[#This Row],[Engagement Score]]<50,"Low",EmployeeData[[#This Row],[Engagement Score]] <70,"Moderate", EmployeeData[[#This Row],[Engagement Score]]<85,"High",TRUE,"Very high")} -> Moderate | U9: 9 | V9: 4.6 | W9: Hybrid | X9: No | Y9: 31 | Z9: No | AA9: =IF(EmployeeData[[#This Row],[Attrition]]="Yes",1,0) -> 0
A10: E0009 | B10: =VLOOKUP(EmployeeData[[#This Row],[Employee ID]],GenderData[#All],2,FALSE) -> Male | C10: Operations | D10: Operations | E10: Canada | F10: Professional | G10: 47 | H10: =IF(EmployeeData[[#This Row],[Age]]<=31,"18-31",IF(EmployeeData[[#This Row],[Age]]<=45,"32-45",IF(EmployeeData[[#This Row],[Age]]<=59,"46-59",IF(EmployeeData[[#This Row],[Age]]<=73,"60-73")))) -> 46-59 | I10: 4.1 | J10: =IF(EmployeeData[[#This Row],[Tenure (Years)]]<1,"Less than 1 year",IF(EmployeeData[[#This Row],[Tenure (Years)]]<2,"1-<2 years",IF(EmployeeData[[#This Row],[Tenure (Years)]]<5,"2-<5 years",IF(EmployeeData[[#This Row],[Tenure (Years)]]<10,"5-<10 years",IF(EmployeeData[[#This Row],[Tenure (Years)]]<15,"10-<15 years","16+ years"))))) -> 2-<5 years | K10: 4.1 | L10: 49900 | M10: 1.01 | N10: =IF(EmployeeData[[#This Row],[Compa-Ratio]]<0.85,"less than 0.85",IF(EmployeeData[[#This Row],[Compa-Ratio]]<1,"0.85-<1.00",IF(EmployeeData[[#This Row],[Compa-Ratio]]<1.15,"1.00-<1.15",IF(EmployeeData[[#This Row],[Compa-Ratio]]>=1.15,"1.15+")))) -> 1.00-<1.15 | O10: Exceeds Expectations | P10: No | Q10: 28 | R10: =IF(EmployeeData[[#This Row],[Months Since Salary Increase]]<6,"<6 months",IF(EmployeeData[[#This Row],[Months Since Salary Increase]]<=12,"6-12 months",IF(EmployeeData[[#This Row],[Months Since Salary Increase]]<=24,"13-24 months", IF(EmployeeData[[#This Row],[Months Since Salary Increase]]>24,"24+ months")))) -> 24+ months | S10: 63 | T10: {=_xlfn.IFS(EmployeeData[[#This Row],[Engagement Score]]<50,"Low",EmployeeData[[#This Row],[Engagement Score]] <70,"Moderate", EmployeeData[[#This Row],[Engagement Score]]<85,"High",TRUE,"Very high")} -> Moderate | U10: 8 | V10: 1.1 | W10: Hybrid | X10: Yes | Y10: 13 | Z10: No | AA10: =IF(EmployeeData[[#This Row],[Attrition]]="Yes",1,0) -> 0
A11: E0010 | B11: =VLOOKUP(EmployeeData[[#This Row],[Employee ID]],GenderData[#All],2,FALSE) -> Male | C11: Marketing | D11: Commercial | E11: US | F11: Professional | G11: 33 | H11: =IF(EmployeeData[[#This Row],[Age]]<=31,"18-31",IF(EmployeeData[[#This Row],[Age]]<=45,"32-45",IF(EmployeeData[[#This Row],[Age]]<=59,"46-59",IF(EmployeeData[[#This Row],[Age]]<=73,"60-73")))) -> 32-45 | I11: 5.6 | J11: =IF(EmployeeData[[#This Row],[Tenure (Years)]]<1,"Less than 1 year",IF(EmployeeData[[#This Row],[Tenure (Years)]]<2,"1-<2 years",IF(EmployeeData[[#This Row],[Tenure (Years)]]<5,"2-<5 years",IF(EmployeeData[[#This Row],[Tenure (Years)]]<10,"5-<10 years",IF(EmployeeData[[#This Row],[Tenure (Years)]]<15,"10-<15 years","16+ years"))))) -> 5-<10 years | K11: 5.6 | L11: 50700 | M11: 1.01 | N11: =IF(EmployeeData[[#This Row],[Compa-Ratio]]<0.85,"less than 0.85",IF(EmployeeData[[#This Row],[Compa-Ratio]]<1,"0.85-<1.00",IF(EmployeeData[[#This Row],[Compa-Ratio]]<1.15,"1.00-<1.15",IF(EmployeeData[[#This Row],[Compa-Ratio]]>=1.15,"1.15+")))) -> 1.00-<1.15 | O11: Meets Expectations | P11: No | Q11: 21 | R11: =IF(EmployeeData[[#This Row],[Months Since Salary Increase]]<6,"<6 months",IF(EmployeeData[[#This Row],[Months Since Salary Increase]]<=12,"6-12 months",IF(EmployeeData[[#This Row],[Months Since Salary Increase]]<=24,"13-24 months", IF(EmployeeData[[#This Row],[Months Since Salary Increase]]>24,"24+ months")))) -> 13-24 months | S11: 55 | T11: {=_xlfn.IFS(EmployeeData[[#This Row],[Engagement Score]]<50,"Low",EmployeeData[[#This Row],[Engagement Score]] <70,"Moderate", EmployeeData[[#This Row],[Engagement Score]]<85,"High",TRUE,"Very high")} -> Moderate | U11: 8 | V11: 4.7 | W11: Hybrid | X11: No | Y11: 7 | Z11: Yes | AA11: =IF(EmployeeData[[#This Row],[Attrition]]="Yes",1,0) -> 1
A12: E0011 | B12: =VLOOKUP(EmployeeData[[#This Row],[Employee ID]],GenderData[#All],2,FALSE) -> Female | C12: IT | D12: Technology | E12: UK | F12: Professional | G12: 32 | H12: =IF(EmployeeData[[#This Row],[Age]]<=31,"18-31",IF(EmployeeData[[#This Row],[Age]]<=45,"32-45",IF(EmployeeData[[#This Row],[Age]]<=59,"46-59",IF(EmployeeData[[#This Row],[Age]]<=73,"60-73")))) -> 32-45 | I12: 0.9 | J12: =IF(EmployeeData[[#This Row],[Tenure (Years)]]<1,"Less than 1 year",IF(EmployeeData[[#This Row],[Tenure (Years)]]<2,"1-<2 years",IF(EmployeeData[[#This Row],[Tenure (Years)]]<5,"2-<5 years",IF(EmployeeData[[#This Row],[Tenure (Years)]]<10,"5-<10 years",IF(EmployeeData[[#This Row],[Tenure (Years)]]<15,"10-<15 years","16+ years"))))) -> Less than 1 year | K12: 0.9 | L12: 49500 | M12: 1.03 | N12: =IF(EmployeeData[[#This Row],[Compa-Ratio]]<0.85,"less than 0.85",IF(EmployeeData[[#This Row],[Compa-Ratio]]<1,"0.85-<1.00",IF(EmployeeData[[#This Row],[Compa-Ratio]]<1.15,"1.00-<1.15",IF(EmployeeData[[#This Row],[Compa-Ratio]]>=1.15,"1.15+")))) -> 1.00-<1.15 | O12: Exceeds Expectations | P12: No | Q12: 17 | R12: =IF(EmployeeData[[#This Row],[Months Since Salary Increase]]<6,"<6 months",IF(EmployeeData[[#This Row],[Months Since Salary Increase]]<=12,"6-12 months",IF(EmployeeData[[#This Row],[Months Since Salary Increase]]<=24,"13-24 months", IF(EmployeeData[[#This Row],[Months Since Salary Increase]]>24,"24+ months")))) -> 13-24 months | S12: 70 | T12: {=_xlfn.IFS(EmployeeData[[#This Row],[Engagement Score]]<50,"Low",EmployeeData[[#This Row],[Engagement Score]] <70,"Moderate", EmployeeData[[#This Row],[Engagement Score]]<85,"High",TRUE,"Very high")} -> High | U12: 5 | V12: 8.4 | W12: Hybrid | X12: No | Y12: 8 | Z12: Yes | AA12: =IF(EmployeeData[[#This Row],[Attrition]]="Yes",1,0) -> 1
A13: E0012 | B13: =VLOOKUP(EmployeeData[[#This Row],[Employee ID]],GenderData[#All],2,FALSE) -> Female | C13: Claims | D13: Insurance | E13: UK | F13: Senior Manager | G13: 52 | H13: =IF(EmployeeData[[#This Row],[Age]]<=31,"18-31",IF(EmployeeData[[#This Row],[Age]]<=45,"32-45",IF(EmployeeData[[#This Row],[Age]]<=59,"46-59",IF(EmployeeData[[#This Row],[Age]]<=73,"60-73")))) -> 46-59 | I13: 2.6 | J13: =IF(EmployeeData[[#This Row],[Tenure (Years)]]<1,"Less than 1 year",IF(EmployeeData[[#This Row],[Tenure (Years)]]<2,"1-<2 years",IF(EmployeeData[[#This Row],[Tenure (Years)]]<5,"2-<5 years",IF(EmployeeData[[#This Row],[Tenure (Years)]]<10,"5-<10 years",IF(EmployeeData[[#This Row],[Tenure (Years)]]<15,"10-<15 years","16+ years"))))) -> 2-<5 years | K13: 2.4 | L13: 92500 | M13: 0.91 | N13: =IF(EmployeeData[[#This Row],[Compa-Ratio]]<0.85,"less than 0.85",IF(EmployeeData[[#This Row],[Compa-Ratio]]<1,"0.85-<1.00",IF(EmployeeData[[#This Row],[Compa-Ratio]]<1.15,"1.00-<1.15",IF(EmployeeData[[#This Row],[Compa-Ratio]]>=1.15,"1.15+")))) -> 0.85-<1.00 | O13: Exceeds Expectations | P13: No | Q13: 29 | R13: =IF(EmployeeData[[#This Row],[Months Since Salary Increase]]<6,"<6 months",IF(EmployeeData[[#This Row],[Months Since Salary Increase]]<=12,"6-12 months",IF(EmployeeData[[#This Row],[Months Since Salary Increase]]<=24,"13-24 months", IF(EmployeeData[[#This Row],[Months Since Salary Increase]]>24,"24+ months")))) -> 24+ months | S13: 80 | T13: {=_xlfn.IFS(EmployeeData[[#This Row],[Engagement Score]]<50,"Low",EmployeeData[[#This Row],[Engagement Score]] <70,"Moderate", EmployeeData[[#This Row],[Engagement Score]]<85,"High",TRUE,"Very high")} -> High | U13: 2 | V13: 2.1 | W13: Hybrid | X13: No | Y13: 31 | Z13: No | AA13: =IF(EmployeeData[[#This Row],[Attrition]]="Yes",1,0) -> 0
... A1001: E1000 | B1001: =VLOOKUP(EmployeeData[[#This Row],[Employee ID]],GenderData[#All],2,FALSE) -> Male | C1001: Sales | D1001: Commercial | E1001: UK | F1001: Professional | G1001: 38 | H1001: =IF(EmployeeData[[#This Row],[Age]]<=31,"18-31",IF(EmployeeData[[#This Row],[Age]]<=45,"32-45",IF(EmployeeData[[#This Row],[Age]]<=59,"46-59",IF(EmployeeData[[#This Row],[Age]]<=73,"60-73")))) -> 32-45 | I1001: 14 | J1001: =IF(EmployeeData[[#This Row],[Tenure (Years)]]<1,"Less than 1 year",IF(EmployeeData[[#This Row],[Tenure (Years)]]<2,"1-<2 years",IF(EmployeeData[[#This Row],[Tenure (Years)]]<5,"2-<5 years",IF(EmployeeData[[#This Row],[Tenure (Years)]]<10,"5-<10 years",IF(EmployeeData[[#This Row],[Tenure (Years)]]<15,"10-<15 years","16+ years"))))) -> 10-<15 years | K1001: 3.7 | L1001: 56400 | M1001: 1.18 | N1001: =IF(EmployeeData[[#This Row],[Compa-Ratio]]<0.85,"less than 0.85",IF(EmployeeData[[#This Row],[Compa-Ratio]]<1,"0.85-<1.00",IF(EmployeeData[[#This Row],[Compa-Ratio]]<1.15,"1.00-<1.15",IF(EmployeeData[[#This Row],[Compa-Ratio]]>=1.15,"1.15+")))) -> 1.15+ | O1001: Exceeds Expectations | P1001: No | Q1001: 17 | R1001: =IF(EmployeeData[[#This Row],[Months Since Salary Increase]]<6,"<6 months",IF(EmployeeData[[#This Row],[Months Since Salary Increase]]<=12,"6-12 months",IF(EmployeeData[[#This Row],[Months Since Salary Increase]]<=24,"13-24 months", IF(EmployeeData[[#This Row],[Months Since Salary Increase]]>24,"24+ months")))) -> 13-24 months | S1001: 85 | T1001: {=_xlfn.IFS(EmployeeData[[#This Row],[Engagement Score]]<50,"Low",EmployeeData[[#This Row],[Engagement Score]] <70,"Moderate", EmployeeData[[#This Row],[Engagement Score]]<85,"High",TRUE,"Very high")} -> Very high | U1001: 6 | V1001: 1.2 | W1001: Remote | X1001: No | Y1001: 31 | Z1001: No | AA1001: =IF(EmployeeData[[#This Row],[Attrition]]="Yes",1,0) -> 0

Sheet Data Dictionary
A1: Field | B1: Description
A2: Employee ID | B2: Unique employee identifier
A3: Department | B3: Employee department
A4: Business Unit | B4: Broader business grouping
A5: Country | B5: Employee country
A6: Job Level | B6: Job seniority level
A7: Age | B7: Age in years
A8: Tenure (Years) | B8: Years with organisation
A9: Time in Role (Years) | B9: Years in current role
A10: Annual Salary | B10: Annual base salary (GBP-equivalent)
A11: Compa-Ratio | B11: Salary relative to reference midpoint for job level
A12: Performance Rating | B12: Latest performance rating
... A21: Attrition | B21: Whether employee left the organisation

Sheet Action plan
A1: Subject: Launch: Data-Driven Attrition Risk Calculator & User Guide
A2: Team,
A3: As part of our commitment to proactive talent management, we are officially launching our new Data-Driven Attrition Risk Calculator.
A4: Built directly within Excel using historical company data, this tool moves us away from guesswork. It allows HR Business Partners to input an employee’s profile and instantly generate an individual 0% to 100% Flight Risk Probability Score.
A5: The calculator tab is now active in our workforce planning file. Please review the simple user guide below to ensure your evaluations are mathematically accurate.
A7: 📖 How to Use the Calculator
A8: Open the Risk Calculator tab. You will see a column labeled User Input (Column C). To evaluate an employee, simply fill out Column C from top to bottom based on these rules:
A9: 1. The Intercept Row (Row 5)
A10: Rule: Always leave this set to 1. This is a mathematical anchor required by the model. Do not alter it.
A11: 2. Numerical Rows (Age, Tenure, Salary Metrics)
A12: Rule: Type the actual, exact number for the employee.
A13: Examples: If the employee is 34 years old, type 34. If they have been with the company for 3 years, type 3.
... A35: Workforce Analytics & HR Strategy
